[
  {
    "partId": 384,
    "stateCode": "S15",
    "stateName": "Meghalaya",
    "districtCode": "S1501",
    "districtName": "WEST JAINTIA HILLS",
    "acNumber": 7,
    "acName": "AMLAREM",
    "partNumber": 1,
    "partName": "DEMTHRING A (MALE)",
    "lat": 25.26981745,
    "lon": 92.09241681588394
  },
  {
    "partId": 385,
    "stateCode": "S15",
    "stateName": "Meghalaya",
    "districtCode": "S1501",
    "districtName": "WEST JAINTIA HILLS",
    "acNumber": 7,
    "acName": "AMLAREM",
    "partNumber": 2,
    "partName": "DEMTHRING B (FEMALE)",
    "lat": 25.26981745,
    "lon": 92.09241681588394
  },
  {
    "partId": 386,
    "stateCode": "S15",
    "stateName": "Meghalaya",
    "districtCode": "S1501",
    "districtName": "WEST JAINTIA HILLS",
    "acNumber": 7,
    "acName": "AMLAREM",
    "partNumber": 3,
    "partName": "SHYRMANG",
    "lat": 25.26981745,
    "lon": 92.09241681588394
  },
  {
    "partId": 387,
    "stateCode": "S15",
    "stateName": "Meghalaya",
    "districtCode": "S1501",
    "districtName": "WEST JAINTIA HILLS",
    "acNumber": 7,
    "acName": "AMLAREM",
    "partNumber": 4,
    "partName": "IONGNOH",
    "lat": 25.26981745,
    "lon": 92.09241681588394
  },
  {
    "partId": 388,
    "stateCode": "S15",
    "stateName": "Meghalaya",
    "districtCode": "S1501",
    "districtName": "WEST JAINTIA HILLS",
    "acNumber": 7,
    "acName": "AMLAREM",
    "partNumber": 5,
    "partName": "PYNTHORLANGTEIN",
    "lat": 25.4175959,
    "lon": 92.1554941
  },
  {
    "partId": 389,
    "stateCode": "S15",
    "stateName": "Meghalaya",
    "districtCode": "S1501",
    "districtName": "WEST JAINTIA HILLS",
    "acNumber": 7,
    "acName": "AMLAREM",
    "partNumber": 6,
    "partName": "MUPHLANG",
    "lat": 25.26981745,
    "lon": 92.09241681588394
  },
  {
    "partId": 390,
    "stateCode": "S15",
    "stateName": "Meghalaya",
    "districtCode": "S1501",
    "districtName": "WEST JAINTIA HILLS",
    "acNumber": 7,
    "acName": "AMLAREM",
    "partNumber": 7,
    "partName": "MUSTEM A (MALE)",
    "lat": 25.26981745,
    "lon": 92.09241681588394
  },
  {
    "partId": 391,
    "stateCode": "S15",
    "stateName": "Meghalaya",
    "districtCode": "S1501",
    "districtName": "WEST JAINTIA HILLS",
    "acNumber": 7,
    "acName": "AMLAREM",
    "partNumber": 8,
    "partName": "MUSTEM B(FEMALE)",
    "lat": 25.26981745,
    "lon": 92.09241681588394
  },
  {
    "partId": 392,
    "stateCode": "S15",
    "stateName": "Meghalaya",
    "districtCode": "S1501",
    "districtName": "WEST JAINTIA HILLS",
    "acNumber": 7,
    "acName": "AMLAREM",
    "partNumber": 9,
    "partName": "MOOSAKHIA",
    "lat": 25.26981745,
    "lon": 92.09241681588394
  },
  {
    "partId": 393,
    "stateCode": "S15",
    "stateName": "Meghalaya",
    "districtCode": "S1501",
    "districtName": "WEST JAINTIA HILLS",
    "acNumber": 7,
    "acName": "AMLAREM",
    "partNumber": 10,
    "partName": "SAMANONG",
    "lat": 25.26981745,
    "lon": 92.09241681588394
  },
  {
    "partId": 394,
    "stateCode": "S15",
    "stateName": "Meghalaya",
    "districtCode": "S1501",
    "districtName": "WEST JAINTIA HILLS",
    "acNumber": 7,
    "acName": "AMLAREM",
    "partNumber": 11,
    "partName": "MUPYUT A (MALE)",
    "lat": 25.26981745,
    "lon": 92.09241681588394
  },
  {
    "partId": 395,
    "stateCode": "S15",
    "stateName": "Meghalaya",
    "districtCode": "S1501",
    "districtName": "WEST JAINTIA HILLS",
    "acNumber": 7,
    "acName": "AMLAREM",
    "partNumber": 12,
    "partName": "MUPYUT B(FEMALE)",
    "lat": 25.26981745,
    "lon": 92.09241681588394
  },
  {
    "partId": 396,
    "stateCode": "S15",
    "stateName": "Meghalaya",
    "districtCode": "S1501",
    "districtName": "WEST JAINTIA HILLS",
    "acNumber": 7,
    "acName": "AMLAREM",
    "partNumber": 13,
    "partName": "SHKENPYRSIT",
    "lat": 25.26981745,
    "lon": 92.09241681588394
  },
  {
    "partId": 397,
    "stateCode": "S15",
    "stateName": "Meghalaya",
    "districtCode": "S1501",
    "districtName": "WEST JAINTIA HILLS",
    "acNumber": 7,
    "acName": "AMLAREM",
    "partNumber": 14,
    "partName": "UMSALANG",
    "lat": 25.26981745,
    "lon": 92.09241681588394
  },
  {
    "partId": 398,
    "stateCode": "S15",
    "stateName": "Meghalaya",
    "districtCode": "S1501",
    "districtName": "WEST JAINTIA HILLS",
    "acNumber": 7,
    "acName": "AMLAREM",
    "partNumber": 15,
    "partName": "SHKENTALANG",
    "lat": 25.26981745,
    "lon": 92.09241681588394
  },
  {
    "partId": 399,
    "stateCode": "S15",
    "stateName": "Meghalaya",
    "districtCode": "S1501",
    "districtName": "WEST JAINTIA HILLS",
    "acNumber": 7,
    "acName": "AMLAREM",
    "partNumber": 16,
    "partName": "JARAIN A",
    "lat": 25.26981745,
    "lon": 92.09241681588394
  },
  {
    "partId": 400,
    "stateCode": "S15",
    "stateName": "Meghalaya",
    "districtCode": "S1501",
    "districtName": "WEST JAINTIA HILLS",
    "acNumber": 7,
    "acName": "AMLAREM",
    "partNumber": 17,
    "partName": "JARAIN B",
    "lat": 25.26981745,
    "lon": 92.09241681588394
  },
  {
    "partId": 401,
    "stateCode": "S15",
    "stateName": "Meghalaya",
    "districtCode": "S1501",
    "districtName": "WEST JAINTIA HILLS",
    "acNumber": 7,
    "acName": "AMLAREM",
    "partNumber": 18,
    "partName": "THANGBULI A (MALE)",
    "lat": 25.26981745,
    "lon": 92.09241681588394
  },
  {
    "partId": 402,
    "stateCode": "S15",
    "stateName": "Meghalaya",
    "districtCode": "S1501",
    "districtName": "WEST JAINTIA HILLS",
    "acNumber": 7,
    "acName": "AMLAREM",
    "partNumber": 19,
    "partName": "THANGBULI B (FEMALE)",
    "lat": 25.26981745,
    "lon": 92.09241681588394
  },
  {
    "partId": 403,
    "stateCode": "S15",
    "stateName": "Meghalaya",
    "districtCode": "S1501",
    "districtName": "WEST JAINTIA HILLS",
    "acNumber": 7,
    "acName": "AMLAREM",
    "partNumber": 20,
    "partName": "UMLADKHUR",
    "lat": 25.26981745,
    "lon": 92.09241681588394
  },
  {
    "partId": 404,
    "stateCode": "S15",
    "stateName": "Meghalaya",
    "districtCode": "S1501",
    "districtName": "WEST JAINTIA HILLS",
    "acNumber": 7,
    "acName": "AMLAREM",
    "partNumber": 21,
    "partName": "AMLAREM A",
    "lat": 25.2859223,
    "lon": 92.1043346
  },
  {
    "partId": 405,
    "stateCode": "S15",
    "stateName": "Meghalaya",
    "districtCode": "S1501",
    "districtName": "WEST JAINTIA HILLS",
    "acNumber": 7,
    "acName": "AMLAREM",
    "partNumber": 22,
    "partName": "AMLAREM B",
    "lat": 25.2857614,
    "lon": 92.1066919
  },
  {
    "partId": 406,
    "stateCode": "S15",
    "stateName": "Meghalaya",
    "districtCode": "S1501",
    "districtName": "WEST JAINTIA HILLS",
    "acNumber": 7,
    "acName": "AMLAREM",
    "partNumber": 23,
    "partName": "PDENGKARONG",
    "lat": 25.26981745,
    "lon": 92.09241681588394
  },
  {
    "partId": 407,
    "stateCode": "S15",
    "stateName": "Meghalaya",
    "districtCode": "S1501",
    "districtName": "WEST JAINTIA HILLS",
    "acNumber": 7,
    "acName": "AMLAREM",
    "partNumber": 24,
    "partName": "AMTAPOH",
    "lat": 25.26981745,
    "lon": 92.09241681588394
  },
  {
    "partId": 408,
    "stateCode": "S15",
    "stateName": "Meghalaya",
    "districtCode": "S1501",
    "districtName": "WEST JAINTIA HILLS",
    "acNumber": 7,
    "acName": "AMLAREM",
    "partNumber": 25,
    "partName": "AMKHLOO PAMTBUH",
    "lat": 25.26981745,
    "lon": 92.09241681588394
  },
  {
    "partId": 409,
    "stateCode": "S15",
    "stateName": "Meghalaya",
    "districtCode": "S1501",
    "districtName": "WEST JAINTIA HILLS",
    "acNumber": 7,
    "acName": "AMLAREM",
    "partNumber": 26,
    "partName": "PADUBAH A (MALE)",
    "lat": 25.26981745,
    "lon": 92.09241681588394
  },
  {
    "partId": 410,
    "stateCode": "S15",
    "stateName": "Meghalaya",
    "districtCode": "S1501",
    "districtName": "WEST JAINTIA HILLS",
    "acNumber": 7,
    "acName": "AMLAREM",
    "partNumber": 27,
    "partName": "PADUBAH B (FEMALE)",
    "lat": 25.26981745,
    "lon": 92.09241681588394
  },
  {
    "partId": 411,
    "stateCode": "S15",
    "stateName": "Meghalaya",
    "districtCode": "S1501",
    "districtName": "WEST JAINTIA HILLS",
    "acNumber": 7,
    "acName": "AMLAREM",
    "partNumber": 28,
    "partName": "MAWNGAP",
    "lat": 25.26981745,
    "lon": 92.09241681588394
  },
  {
    "partId": 412,
    "stateCode": "S15",
    "stateName": "Meghalaya",
    "districtCode": "S1501",
    "districtName": "WEST JAINTIA HILLS",
    "acNumber": 7,
    "acName": "AMLAREM",
    "partNumber": 29,
    "partName": "AMMUTONG",
    "lat": 25.26981745,
    "lon": 92.09241681588394
  },
  {
    "partId": 413,
    "stateCode": "S15",
    "stateName": "Meghalaya",
    "districtCode": "S1501",
    "districtName": "WEST JAINTIA HILLS",
    "acNumber": 7,
    "acName": "AMLAREM",
    "partNumber": 30,
    "partName": "MAWLONG",
    "lat": 25.26981745,
    "lon": 92.09241681588394
  },
  {
    "partId": 414,
    "stateCode": "S15",
    "stateName": "Meghalaya",
    "districtCode": "S1501",
    "districtName": "WEST JAINTIA HILLS",
    "acNumber": 7,
    "acName": "AMLAREM",
    "partNumber": 31,
    "partName": "KHONGLAH A",
    "lat": 25.26981745,
    "lon": 92.09241681588394
  },
  {
    "partId": 415,
    "stateCode": "S15",
    "stateName": "Meghalaya",
    "districtCode": "S1501",
    "districtName": "WEST JAINTIA HILLS",
    "acNumber": 7,
    "acName": "AMLAREM",
    "partNumber": 32,
    "partName": "KHONGLAH B",
    "lat": 25.26981745,
    "lon": 92.09241681588394
  },
  {
    "partId": 416,
    "stateCode": "S15",
    "stateName": "Meghalaya",
    "districtCode": "S1501",
    "districtName": "WEST JAINTIA HILLS",
    "acNumber": 7,
    "acName": "AMLAREM",
    "partNumber": 33,
    "partName": "NONGBAREH RIM",
    "lat": 25.26981745,
    "lon": 92.09241681588394
  },
  {
    "partId": 417,
    "stateCode": "S15",
    "stateName": "Meghalaya",
    "districtCode": "S1501",
    "districtName": "WEST JAINTIA HILLS",
    "acNumber": 7,
    "acName": "AMLAREM",
    "partNumber": 34,
    "partName": "NONGBAREH LYNTIAR",
    "lat": 25.26981745,
    "lon": 92.09241681588394
  },
  {
    "partId": 418,
    "stateCode": "S15",
    "stateName": "Meghalaya",
    "districtCode": "S1501",
    "districtName": "WEST JAINTIA HILLS",
    "acNumber": 7,
    "acName": "AMLAREM",
    "partNumber": 35,
    "partName": "AMKOI",
    "lat": 25.26981745,
    "lon": 92.09241681588394
  },
  {
    "partId": 419,
    "stateCode": "S15",
    "stateName": "Meghalaya",
    "districtCode": "S1501",
    "districtName": "WEST JAINTIA HILLS",
    "acNumber": 7,
    "acName": "AMLAREM",
    "partNumber": 36,
    "partName": "KUDENG RIM",
    "lat": 25.26981745,
    "lon": 92.09241681588394
  },
  {
    "partId": 420,
    "stateCode": "S15",
    "stateName": "Meghalaya",
    "districtCode": "S1501",
    "districtName": "WEST JAINTIA HILLS",
    "acNumber": 7,
    "acName": "AMLAREM",
    "partNumber": 37,
    "partName": "SHNONGPDENG",
    "lat": 25.26981745,
    "lon": 92.09241681588394
  },
  {
    "partId": 421,
    "stateCode": "S15",
    "stateName": "Meghalaya",
    "districtCode": "S1501",
    "districtName": "WEST JAINTIA HILLS",
    "acNumber": 7,
    "acName": "AMLAREM",
    "partNumber": 38,
    "partName": "KONGWANG",
    "lat": 25.26981745,
    "lon": 92.09241681588394
  },
  {
    "partId": 422,
    "stateCode": "S15",
    "stateName": "Meghalaya",
    "districtCode": "S1501",
    "districtName": "WEST JAINTIA HILLS",
    "acNumber": 7,
    "acName": "AMLAREM",
    "partNumber": 39,
    "partName": "LAMIN SHNONG A (MALE)",
    "lat": 25.26981745,
    "lon": 92.09241681588394
  },
  {
    "partId": 423,
    "stateCode": "S15",
    "stateName": "Meghalaya",
    "districtCode": "S1501",
    "districtName": "WEST JAINTIA HILLS",
    "acNumber": 7,
    "acName": "AMLAREM",
    "partNumber": 40,
    "partName": "LAMIN SHNONG B (FEMALE)",
    "lat": 25.26981745,
    "lon": 92.09241681588394
  },
  {
    "partId": 424,
    "stateCode": "S15",
    "stateName": "Meghalaya",
    "districtCode": "S1501",
    "districtName": "WEST JAINTIA HILLS",
    "acNumber": 7,
    "acName": "AMLAREM",
    "partNumber": 41,
    "partName": "KUDENG THYMMAI",
    "lat": 25.26981745,
    "lon": 92.09241681588394
  },
  {
    "partId": 425,
    "stateCode": "S15",
    "stateName": "Meghalaya",
    "districtCode": "S1501",
    "districtName": "WEST JAINTIA HILLS",
    "acNumber": 7,
    "acName": "AMLAREM",
    "partNumber": 42,
    "partName": "PDENGSHAKAP A (MALE)",
    "lat": 25.26981745,
    "lon": 92.09241681588394
  },
  {
    "partId": 426,
    "stateCode": "S15",
    "stateName": "Meghalaya",
    "districtCode": "S1501",
    "districtName": "WEST JAINTIA HILLS",
    "acNumber": 7,
    "acName": "AMLAREM",
    "partNumber": 43,
    "partName": "PDENGSHAKAP B (FEMALE)",
    "lat": 25.26981745,
    "lon": 92.09241681588394
  },
  {
    "partId": 427,
    "stateCode": "S15",
    "stateName": "Meghalaya",
    "districtCode": "S1501",
    "districtName": "WEST JAINTIA HILLS",
    "acNumber": 7,
    "acName": "AMLAREM",
    "partNumber": 44,
    "partName": "NONGTALANG AMLARIANG",
    "lat": 25.26981745,
    "lon": 92.09241681588394
  },
  {
    "partId": 428,
    "stateCode": "S15",
    "stateName": "Meghalaya",
    "districtCode": "S1501",
    "districtName": "WEST JAINTIA HILLS",
    "acNumber": 7,
    "acName": "AMLAREM",
    "partNumber": 45,
    "partName": "NONGTALANG PDENGSHNONG A(MALE)",
    "lat": 25.26981745,
    "lon": 92.09241681588394
  },
  {
    "partId": 429,
    "stateCode": "S15",
    "stateName": "Meghalaya",
    "districtCode": "S1501",
    "districtName": "WEST JAINTIA HILLS",
    "acNumber": 7,
    "acName": "AMLAREM",
    "partNumber": 46,
    "partName": "NONGTALANG PDENGSHNONG B (FEMALE)",
    "lat": 25.26981745,
    "lon": 92.09241681588394
  },
  {
    "partId": 430,
    "stateCode": "S15",
    "stateName": "Meghalaya",
    "districtCode": "S1501",
    "districtName": "WEST JAINTIA HILLS",
    "acNumber": 7,
    "acName": "AMLAREM",
    "partNumber": 47,
    "partName": "NONGTALANG MISSION",
    "lat": 25.21106,
    "lon": 92.059372
  },
  {
    "partId": 431,
    "stateCode": "S15",
    "stateName": "Meghalaya",
    "districtCode": "S1501",
    "districtName": "WEST JAINTIA HILLS",
    "acNumber": 7,
    "acName": "AMLAREM",
    "partNumber": 48,
    "partName": "NONGTALANG KHLACHYMPA",
    "lat": 25.26981745,
    "lon": 92.09241681588394
  },
  {
    "partId": 432,
    "stateCode": "S15",
    "stateName": "Meghalaya",
    "districtCode": "S1501",
    "districtName": "WEST JAINTIA HILLS",
    "acNumber": 7,
    "acName": "AMLAREM",
    "partNumber": 49,
    "partName": "NONGTALANG AMSOHMEHELENG",
    "lat": 25.26981745,
    "lon": 92.09241681588394
  },
  {
    "partId": 433,
    "stateCode": "S15",
    "stateName": "Meghalaya",
    "districtCode": "S1501",
    "districtName": "WEST JAINTIA HILLS",
    "acNumber": 7,
    "acName": "AMLAREM",
    "partNumber": 50,
    "partName": "AMJAJER ROKO",
    "lat": 25.26981745,
    "lon": 92.09241681588394
  },
  {
    "partId": 434,
    "stateCode": "S15",
    "stateName": "Meghalaya",
    "districtCode": "S1501",
    "districtName": "WEST JAINTIA HILLS",
    "acNumber": 7,
    "acName": "AMLAREM",
    "partNumber": 51,
    "partName": "SOHKHA MISSION",
    "lat": 25.2118623,
    "lon": 92.0352763
  },
  {
    "partId": 435,
    "stateCode": "S15",
    "stateName": "Meghalaya",
    "districtCode": "S1501",
    "districtName": "WEST JAINTIA HILLS",
    "acNumber": 7,
    "acName": "AMLAREM",
    "partNumber": 52,
    "partName": "SOHKHA SHNONG",
    "lat": 25.2150461,
    "lon": 92.0351851
  },
  {
    "partId": 436,
    "stateCode": "S15",
    "stateName": "Meghalaya",
    "districtCode": "S1501",
    "districtName": "WEST JAINTIA HILLS",
    "acNumber": 7,
    "acName": "AMLAREM",
    "partNumber": 53,
    "partName": "SOHKHA MODEL MATHMAT",
    "lat": 25.26981745,
    "lon": 92.09241681588394
  },
  {
    "partId": 437,
    "stateCode": "S15",
    "stateName": "Meghalaya",
    "districtCode": "S1501",
    "districtName": "WEST JAINTIA HILLS",
    "acNumber": 7,
    "acName": "AMLAREM",
    "partNumber": 54,
    "partName": "DARRANG A (MALE)",
    "lat": 25.26981745,
    "lon": 92.09241681588394
  },
  {
    "partId": 438,
    "stateCode": "S15",
    "stateName": "Meghalaya",
    "districtCode": "S1501",
    "districtName": "WEST JAINTIA HILLS",
    "acNumber": 7,
    "acName": "AMLAREM",
    "partNumber": 55,
    "partName": "DARRANG B (FEMALE)",
    "lat": 25.26981745,
    "lon": 92.09241681588394
  },
  {
    "partId": 439,
    "stateCode": "S15",
    "stateName": "Meghalaya",
    "districtCode": "S1501",
    "districtName": "WEST JAINTIA HILLS",
    "acNumber": 7,
    "acName": "AMLAREM",
    "partNumber": 56,
    "partName": "LYMBA",
    "lat": 25.26981745,
    "lon": 92.09241681588394
  },
  {
    "partId": 440,
    "stateCode": "S15",
    "stateName": "Meghalaya",
    "districtCode": "S1501",
    "districtName": "WEST JAINTIA HILLS",
    "acNumber": 7,
    "acName": "AMLAREM",
    "partNumber": 57,
    "partName": "BAKUR A (MALE)",
    "lat": 25.26981745,
    "lon": 92.09241681588394
  },
  {
    "partId": 441,
    "stateCode": "S15",
    "stateName": "Meghalaya",
    "districtCode": "S1501",
    "districtName": "WEST JAINTIA HILLS",
    "acNumber": 7,
    "acName": "AMLAREM",
    "partNumber": 58,
    "partName": "BAKUR B (FEMALE)",
    "lat": 25.26981745,
    "lon": 92.09241681588394
  },
  {
    "partId": 442,
    "stateCode": "S15",
    "stateName": "Meghalaya",
    "districtCode": "S1501",
    "districtName": "WEST JAINTIA HILLS",
    "acNumber": 7,
    "acName": "AMLAREM",
    "partNumber": 59,
    "partName": "DAWKI",
    "lat": 25.1856343,
    "lon": 92.0215717
  },
  {
    "partId": 443,
    "stateCode": "S15",
    "stateName": "Meghalaya",
    "districtCode": "S1501",
    "districtName": "WEST JAINTIA HILLS",
    "acNumber": 7,
    "acName": "AMLAREM",
    "partNumber": 60,
    "partName": "AMLYMPIANG",
    "lat": 25.26981745,
    "lon": 92.09241681588394
  },
  {
    "partId": 444,
    "stateCode": "S15",
    "stateName": "Meghalaya",
    "districtCode": "S1501",
    "districtName": "WEST JAINTIA HILLS",
    "acNumber": 7,
    "acName": "AMLAREM",
    "partNumber": 61,
    "partName": "RHONGKUM",
    "lat": 25.26981745,
    "lon": 92.09241681588394
  },
  {
    "partId": 445,
    "stateCode": "S15",
    "stateName": "Meghalaya",
    "districtCode": "S1501",
    "districtName": "WEST JAINTIA HILLS",
    "acNumber": 7,
    "acName": "AMLAREM",
    "partNumber": 62,
    "partName": "TWAH-U-SDIAH",
    "lat": 25.26981745,
    "lon": 92.09241681588394
  },
  {
    "partId": 446,
    "stateCode": "S15",
    "stateName": "Meghalaya",
    "districtCode": "S1501",
    "districtName": "WEST JAINTIA HILLS",
    "acNumber": 7,
    "acName": "AMLAREM",
    "partNumber": 63,
    "partName": "JONGUSHEN",
    "lat": 25.26981745,
    "lon": 92.09241681588394
  },
  {
    "partId": 447,
    "stateCode": "S15",
    "stateName": "Meghalaya",
    "districtCode": "S1501",
    "districtName": "WEST JAINTIA HILLS",
    "acNumber": 7,
    "acName": "AMLAREM",
    "partNumber": 64,
    "partName": "AMSOHTAI",
    "lat": 25.26981745,
    "lon": 92.09241681588394
  },
  {
    "partId": 448,
    "stateCode": "S15",
    "stateName": "Meghalaya",
    "districtCode": "S1501",
    "districtName": "WEST JAINTIA HILLS",
    "acNumber": 7,
    "acName": "AMLAREM",
    "partNumber": 65,
    "partName": "PDENGKSEH",
    "lat": 25.26981745,
    "lon": 92.09241681588394
  },
  {
    "partId": 449,
    "stateCode": "S15",
    "stateName": "Meghalaya",
    "districtCode": "S1501",
    "districtName": "WEST JAINTIA HILLS",
    "acNumber": 7,
    "acName": "AMLAREM",
    "partNumber": 66,
    "partName": "AMJALONG",
    "lat": 25.26981745,
    "lon": 92.09241681588394
  },
  {
    "partId": 450,
    "stateCode": "S15",
    "stateName": "Meghalaya",
    "districtCode": "S1501",
    "districtName": "WEST JAINTIA HILLS",
    "acNumber": 7,
    "acName": "AMLAREM",
    "partNumber": 67,
    "partName": "SYNDAI KMAISHNONG",
    "lat": 25.26981745,
    "lon": 92.09241681588394
  },
  {
    "partId": 451,
    "stateCode": "S15",
    "stateName": "Meghalaya",
    "districtCode": "S1501",
    "districtName": "WEST JAINTIA HILLS",
    "acNumber": 7,
    "acName": "AMLAREM",
    "partNumber": 68,
    "partName": "SYNDAI MISSION",
    "lat": 25.26981745,
    "lon": 92.09241681588394
  },
  {
    "partId": 452,
    "stateCode": "S15",
    "stateName": "Meghalaya",
    "districtCode": "S1501",
    "districtName": "WEST JAINTIA HILLS",
    "acNumber": 7,
    "acName": "AMLAREM",
    "partNumber": 69,
    "partName": "AMLARI MODEL",
    "lat": 25.26981745,
    "lon": 92.09241681588394
  },
  {
    "partId": 453,
    "stateCode": "S15",
    "stateName": "Meghalaya",
    "districtCode": "S1501",
    "districtName": "WEST JAINTIA HILLS",
    "acNumber": 7,
    "acName": "AMLAREM",
    "partNumber": 70,
    "partName": "TRANGBLANG MISSION",
    "lat": 25.26981745,
    "lon": 92.09241681588394
  },
  {
    "partId": 454,
    "stateCode": "S15",
    "stateName": "Meghalaya",
    "districtCode": "S1501",
    "districtName": "WEST JAINTIA HILLS",
    "acNumber": 7,
    "acName": "AMLAREM",
    "partNumber": 71,
    "partName": "SATPATOR",
    "lat": 25.26981745,
    "lon": 92.09241681588394
  },
  {
    "partId": 455,
    "stateCode": "S15",
    "stateName": "Meghalaya",
    "districtCode": "S1501",
    "districtName": "WEST JAINTIA HILLS",
    "acNumber": 7,
    "acName": "AMLAREM",
    "partNumber": 72,
    "partName": "AMSKU",
    "lat": 25.26981745,
    "lon": 92.09241681588394
  },
  {
    "partId": 456,
    "stateCode": "S15",
    "stateName": "Meghalaya",
    "districtCode": "S1501",
    "districtName": "WEST JAINTIA HILLS",
    "acNumber": 7,
    "acName": "AMLAREM",
    "partNumber": 73,
    "partName": "MUKTAPUR",
    "lat": 25.1651253,
    "lon": 92.1259474
  },
  {
    "partId": 457,
    "stateCode": "S15",
    "stateName": "Meghalaya",
    "districtCode": "S1501",
    "districtName": "WEST JAINTIA HILLS",
    "acNumber": 7,
    "acName": "AMLAREM",
    "partNumber": 74,
    "partName": "HAWAIBHOI (AMSE)",
    "lat": 25.26981745,
    "lon": 92.09241681588394
  },
  {
    "partId": 458,
    "stateCode": "S15",
    "stateName": "Meghalaya",
    "districtCode": "S1501",
    "districtName": "WEST JAINTIA HILLS",
    "acNumber": 7,
    "acName": "AMLAREM",
    "partNumber": 75,
    "partName": "HAWAI SUTNGA",
    "lat": 25.26981745,
    "lon": 92.09241681588394
  },
  {
    "partId": 459,
    "stateCode": "S15",
    "stateName": "Meghalaya",
    "districtCode": "S1501",
    "districtName": "WEST JAINTIA HILLS",
    "acNumber": 7,
    "acName": "AMLAREM",
    "partNumber": 76,
    "partName": "AMSOHRHONG",
    "lat": 25.26981745,
    "lon": 92.09241681588394
  },
  {
    "partId": 460,
    "stateCode": "S15",
    "stateName": "Meghalaya",
    "districtCode": "S1501",
    "districtName": "WEST JAINTIA HILLS",
    "acNumber": 7,
    "acName": "AMLAREM",
    "partNumber": 77,
    "partName": "AMTRA",
    "lat": 25.26981745,
    "lon": 92.09241681588394
  },
  {
    "partId": 461,
    "stateCode": "S15",
    "stateName": "Meghalaya",
    "districtCode": "S1501",
    "districtName": "WEST JAINTIA HILLS",
    "acNumber": 7,
    "acName": "AMLAREM",
    "partNumber": 78,
    "partName": "AMLANAI",
    "lat": 25.26981745,
    "lon": 92.09241681588394
  },
  {
    "partId": 462,
    "stateCode": "S15",
    "stateName": "Meghalaya",
    "districtCode": "S1501",
    "districtName": "WEST JAINTIA HILLS",
    "acNumber": 7,
    "acName": "AMLAREM",
    "partNumber": 79,
    "partName": "SANKHAD",
    "lat": 25.26981745,
    "lon": 92.09241681588394
  },
  {
    "partId": 463,
    "stateCode": "S15",
    "stateName": "Meghalaya",
    "districtCode": "S1501",
    "districtName": "WEST JAINTIA HILLS",
    "acNumber": 7,
    "acName": "AMLAREM",
    "partNumber": 80,
    "partName": "PASADWAR",
    "lat": 25.26981745,
    "lon": 92.09241681588394
  },
  {
    "partId": 464,
    "stateCode": "S15",
    "stateName": "Meghalaya",
    "districtCode": "S1501",
    "districtName": "WEST JAINTIA HILLS",
    "acNumber": 7,
    "acName": "AMLAREM",
    "partNumber": 81,
    "partName": "KHARKHANA",
    "lat": 25.1589585,
    "lon": 92.2098827
  },
  {
    "partId": 465,
    "stateCode": "S15",
    "stateName": "Meghalaya",
    "districtCode": "S1501",
    "districtName": "WEST JAINTIA HILLS",
    "acNumber": 7,
    "acName": "AMLAREM",
    "partNumber": 82,
    "partName": "KAMSING",
    "lat": 25.26981745,
    "lon": 92.09241681588394
  },
  {
    "partId": 64,
    "stateCode": "S15",
    "stateName": "Meghalaya",
    "districtCode": "S1501",
    "districtName": "WEST JAINTIA HILLS",
    "acNumber": 2,
    "acName": "JOWAI",
    "partNumber": 1,
    "partName": "MADUR A",
    "lat": 25.4434703,
    "lon": 92.1973181
  },
  {
    "partId": 65,
    "stateCode": "S15",
    "stateName": "Meghalaya",
    "districtCode": "S1501",
    "districtName": "WEST JAINTIA HILLS",
    "acNumber": 2,
    "acName": "JOWAI",
    "partNumber": 2,
    "partName": "MADUR B",
    "lat": 25.4434703,
    "lon": 92.1973181
  },
  {
    "partId": 66,
    "stateCode": "S15",
    "stateName": "Meghalaya",
    "districtCode": "S1501",
    "districtName": "WEST JAINTIA HILLS",
    "acNumber": 2,
    "acName": "JOWAI",
    "partNumber": 3,
    "partName": "NIRIANG",
    "lat": 25.4434703,
    "lon": 92.1973181
  },
  {
    "partId": 67,
    "stateCode": "S15",
    "stateName": "Meghalaya",
    "districtCode": "S1501",
    "districtName": "WEST JAINTIA HILLS",
    "acNumber": 2,
    "acName": "JOWAI",
    "partNumber": 4,
    "partName": "LAD MUKHLA A",
    "lat": 25.4434703,
    "lon": 92.1973181
  },
  {
    "partId": 68,
    "stateCode": "S15",
    "stateName": "Meghalaya",
    "districtCode": "S1501",
    "districtName": "WEST JAINTIA HILLS",
    "acNumber": 2,
    "acName": "JOWAI",
    "partNumber": 5,
    "partName": "LAD MUKHLA B",
    "lat": 25.4434703,
    "lon": 92.1973181
  },
  {
    "partId": 69,
    "stateCode": "S15",
    "stateName": "Meghalaya",
    "districtCode": "S1501",
    "districtName": "WEST JAINTIA HILLS",
    "acNumber": 2,
    "acName": "JOWAI",
    "partNumber": 6,
    "partName": "UMLANGSHOR",
    "lat": 25.4434703,
    "lon": 92.1973181
  },
  {
    "partId": 70,
    "stateCode": "S15",
    "stateName": "Meghalaya",
    "districtCode": "S1501",
    "districtName": "WEST JAINTIA HILLS",
    "acNumber": 2,
    "acName": "JOWAI",
    "partNumber": 7,
    "partName": "MUKHLA SHOHSHRIEH",
    "lat": 25.4434703,
    "lon": 92.1973181
  },
  {
    "partId": 71,
    "stateCode": "S15",
    "stateName": "Meghalaya",
    "districtCode": "S1501",
    "districtName": "WEST JAINTIA HILLS",
    "acNumber": 2,
    "acName": "JOWAI",
    "partNumber": 8,
    "partName": "MUKHLA A (MALE)",
    "lat": 25.4434703,
    "lon": 92.1973181
  },
  {
    "partId": 72,
    "stateCode": "S15",
    "stateName": "Meghalaya",
    "districtCode": "S1501",
    "districtName": "WEST JAINTIA HILLS",
    "acNumber": 2,
    "acName": "JOWAI",
    "partNumber": 9,
    "partName": "MUKHLA B (FEMALE)",
    "lat": 25.4434703,
    "lon": 92.1973181
  },
  {
    "partId": 73,
    "stateCode": "S15",
    "stateName": "Meghalaya",
    "districtCode": "S1501",
    "districtName": "WEST JAINTIA HILLS",
    "acNumber": 2,
    "acName": "JOWAI",
    "partNumber": 10,
    "partName": "MUKHLA MISSION",
    "lat": 25.4434703,
    "lon": 92.1973181
  },
  {
    "partId": 74,
    "stateCode": "S15",
    "stateName": "Meghalaya",
    "districtCode": "S1501",
    "districtName": "WEST JAINTIA HILLS",
    "acNumber": 2,
    "acName": "JOWAI",
    "partNumber": 11,
    "partName": "PHLONGINGKHAW",
    "lat": 25.4434703,
    "lon": 92.1973181
  },
  {
    "partId": 75,
    "stateCode": "S15",
    "stateName": "Meghalaya",
    "districtCode": "S1501",
    "districtName": "WEST JAINTIA HILLS",
    "acNumber": 2,
    "acName": "JOWAI",
    "partNumber": 12,
    "partName": "MOOKYNIANG A (MALE)",
    "lat": 25.4434703,
    "lon": 92.1973181
  },
  {
    "partId": 76,
    "stateCode": "S15",
    "stateName": "Meghalaya",
    "districtCode": "S1501",
    "districtName": "WEST JAINTIA HILLS",
    "acNumber": 2,
    "acName": "JOWAI",
    "partNumber": 13,
    "partName": "MOOKYNIANG B (FEMALE)",
    "lat": 25.4434703,
    "lon": 92.1973181
  },
  {
    "partId": 77,
    "stateCode": "S15",
    "stateName": "Meghalaya",
    "districtCode": "S1501",
    "districtName": "WEST JAINTIA HILLS",
    "acNumber": 2,
    "acName": "JOWAI",
    "partNumber": 14,
    "partName": "MOOPYLLAITSYIAR",
    "lat": 25.4434703,
    "lon": 92.1973181
  },
  {
    "partId": 78,
    "stateCode": "S15",
    "stateName": "Meghalaya",
    "districtCode": "S1501",
    "districtName": "WEST JAINTIA HILLS",
    "acNumber": 2,
    "acName": "JOWAI",
    "partNumber": 15,
    "partName": "KHLIEHTYRSHI",
    "lat": 25.4759461,
    "lon": 92.176552
  },
  {
    "partId": 79,
    "stateCode": "S15",
    "stateName": "Meghalaya",
    "districtCode": "S1501",
    "districtName": "WEST JAINTIA HILLS",
    "acNumber": 2,
    "acName": "JOWAI",
    "partNumber": 16,
    "partName": "MIHMYNTDU LUMPYRDI A (MALE)",
    "lat": 25.4425965,
    "lon": 92.29882747091773
  },
  {
    "partId": 80,
    "stateCode": "S15",
    "stateName": "Meghalaya",
    "districtCode": "S1501",
    "districtName": "WEST JAINTIA HILLS",
    "acNumber": 2,
    "acName": "JOWAI",
    "partNumber": 17,
    "partName": "MIHMYNTDU LUMPYRDI  B(FEMALE)",
    "lat": 25.44396544545455,
    "lon": 92.20801428410012
  },
  {
    "partId": 81,
    "stateCode": "S15",
    "stateName": "Meghalaya",
    "districtCode": "S1501",
    "districtName": "WEST JAINTIA HILLS",
    "acNumber": 2,
    "acName": "JOWAI",
    "partNumber": 18,
    "partName": "MIHMYNTDU LUMPYRTUH A (MALE)",
    "lat": 25.4425965,
    "lon": 92.29882747091773
  },
  {
    "partId": 82,
    "stateCode": "S15",
    "stateName": "Meghalaya",
    "districtCode": "S1501",
    "districtName": "WEST JAINTIA HILLS",
    "acNumber": 2,
    "acName": "JOWAI",
    "partNumber": 19,
    "partName": "MIHMYNTDU LUMPYRTUH B (FEMALE)",
    "lat": 25.4425965,
    "lon": 92.29882747091773
  },
  {
    "partId": 83,
    "stateCode": "S15",
    "stateName": "Meghalaya",
    "districtCode": "S1501",
    "districtName": "WEST JAINTIA HILLS",
    "acNumber": 2,
    "acName": "JOWAI",
    "partNumber": 20,
    "partName": "MOOKYNPHAD MIHMYNTDU",
    "lat": 25.44396544545455,
    "lon": 92.20801428410012
  },
  {
    "partId": 84,
    "stateCode": "S15",
    "stateName": "Meghalaya",
    "districtCode": "S1501",
    "districtName": "WEST JAINTIA HILLS",
    "acNumber": 2,
    "acName": "JOWAI",
    "partNumber": 21,
    "partName": "MIHMYNTDU LUMPYRTUH SALINI COLONY",
    "lat": 25.4434703,
    "lon": 92.1973181
  },
  {
    "partId": 85,
    "stateCode": "S15",
    "stateName": "Meghalaya",
    "districtCode": "S1501",
    "districtName": "WEST JAINTIA HILLS",
    "acNumber": 2,
    "acName": "JOWAI",
    "partNumber": 22,
    "partName": "SABAHMUSWANG A (MALE)",
    "lat": 25.4434703,
    "lon": 92.1973181
  },
  {
    "partId": 86,
    "stateCode": "S15",
    "stateName": "Meghalaya",
    "districtCode": "S1501",
    "districtName": "WEST JAINTIA HILLS",
    "acNumber": 2,
    "acName": "JOWAI",
    "partNumber": 23,
    "partName": "SABAHMUSWANG B(FEMALE)",
    "lat": 25.4434703,
    "lon": 92.1973181
  },
  {
    "partId": 87,
    "stateCode": "S15",
    "stateName": "Meghalaya",
    "districtCode": "S1501",
    "districtName": "WEST JAINTIA HILLS",
    "acNumber": 2,
    "acName": "JOWAI",
    "partNumber": 24,
    "partName": "SOHMYNTING A (MALE)",
    "lat": 25.4425965,
    "lon": 92.29882747091773
  },
  {
    "partId": 88,
    "stateCode": "S15",
    "stateName": "Meghalaya",
    "districtCode": "S1501",
    "districtName": "WEST JAINTIA HILLS",
    "acNumber": 2,
    "acName": "JOWAI",
    "partNumber": 25,
    "partName": "SOHMYNTING B (FEMALE)",
    "lat": 25.4434703,
    "lon": 92.1973181
  },
  {
    "partId": 89,
    "stateCode": "S15",
    "stateName": "Meghalaya",
    "districtCode": "S1501",
    "districtName": "WEST JAINTIA HILLS",
    "acNumber": 2,
    "acName": "JOWAI",
    "partNumber": 26,
    "partName": "SOHMYNTING DONGWAH",
    "lat": 25.4434703,
    "lon": 92.1973181
  },
  {
    "partId": 90,
    "stateCode": "S15",
    "stateName": "Meghalaya",
    "districtCode": "S1501",
    "districtName": "WEST JAINTIA HILLS",
    "acNumber": 2,
    "acName": "JOWAI",
    "partNumber": 27,
    "partName": "IALONG A (MALE)",
    "lat": 25.4434703,
    "lon": 92.1973181
  },
  {
    "partId": 91,
    "stateCode": "S15",
    "stateName": "Meghalaya",
    "districtCode": "S1501",
    "districtName": "WEST JAINTIA HILLS",
    "acNumber": 2,
    "acName": "JOWAI",
    "partNumber": 28,
    "partName": "IALONG B (FEMALE)",
    "lat": 25.4434703,
    "lon": 92.1973181
  },
  {
    "partId": 92,
    "stateCode": "S15",
    "stateName": "Meghalaya",
    "districtCode": "S1501",
    "districtName": "WEST JAINTIA HILLS",
    "acNumber": 2,
    "acName": "JOWAI",
    "partNumber": 29,
    "partName": "IALONG LUTI TUBER",
    "lat": 25.4434703,
    "lon": 92.1973181
  },
  {
    "partId": 93,
    "stateCode": "S15",
    "stateName": "Meghalaya",
    "districtCode": "S1501",
    "districtName": "WEST JAINTIA HILLS",
    "acNumber": 2,
    "acName": "JOWAI",
    "partNumber": 30,
    "partName": "LADTHADLABOH A",
    "lat": 25.4434703,
    "lon": 92.1973181
  },
  {
    "partId": 94,
    "stateCode": "S15",
    "stateName": "Meghalaya",
    "districtCode": "S1501",
    "districtName": "WEST JAINTIA HILLS",
    "acNumber": 2,
    "acName": "JOWAI",
    "partNumber": 31,
    "partName": "CAROLINE COLONY",
    "lat": 25.4434703,
    "lon": 92.1973181
  },
  {
    "partId": 95,
    "stateCode": "S15",
    "stateName": "Meghalaya",
    "districtCode": "S1501",
    "districtName": "WEST JAINTIA HILLS",
    "acNumber": 2,
    "acName": "JOWAI",
    "partNumber": 32,
    "partName": "LADTHADLABOH B",
    "lat": 25.4425965,
    "lon": 92.29882747091773
  },
  {
    "partId": 96,
    "stateCode": "S15",
    "stateName": "Meghalaya",
    "districtCode": "S1501",
    "districtName": "WEST JAINTIA HILLS",
    "acNumber": 2,
    "acName": "JOWAI",
    "partNumber": 33,
    "partName": "LADTHADLABOH C",
    "lat": 25.4434703,
    "lon": 92.1973181
  },
  {
    "partId": 97,
    "stateCode": "S15",
    "stateName": "Meghalaya",
    "districtCode": "S1501",
    "districtName": "WEST JAINTIA HILLS",
    "acNumber": 2,
    "acName": "JOWAI",
    "partNumber": 34,
    "partName": "MOOKYRDUP",
    "lat": 25.4434703,
    "lon": 92.1973181
  },
  {
    "partId": 98,
    "stateCode": "S15",
    "stateName": "Meghalaya",
    "districtCode": "S1501",
    "districtName": "WEST JAINTIA HILLS",
    "acNumber": 2,
    "acName": "JOWAI",
    "partNumber": 35,
    "partName": "DONGMIHSNGI A",
    "lat": 25.4434703,
    "lon": 92.1973181
  },
  {
    "partId": 99,
    "stateCode": "S15",
    "stateName": "Meghalaya",
    "districtCode": "S1501",
    "districtName": "WEST JAINTIA HILLS",
    "acNumber": 2,
    "acName": "JOWAI",
    "partNumber": 36,
    "partName": "DONGMIHSNGI B",
    "lat": 25.4434703,
    "lon": 92.1973181
  },
  {
    "partId": 100,
    "stateCode": "S15",
    "stateName": "Meghalaya",
    "districtCode": "S1501",
    "districtName": "WEST JAINTIA HILLS",
    "acNumber": 2,
    "acName": "JOWAI",
    "partNumber": 37,
    "partName": "IAWMUSIANG A (MALE)",
    "lat": 25.4434703,
    "lon": 92.1973181
  },
  {
    "partId": 101,
    "stateCode": "S15",
    "stateName": "Meghalaya",
    "districtCode": "S1501",
    "districtName": "WEST JAINTIA HILLS",
    "acNumber": 2,
    "acName": "JOWAI",
    "partNumber": 38,
    "partName": "IAWMUSIANG B (FEMALE)",
    "lat": 25.4434703,
    "lon": 92.1973181
  },
  {
    "partId": 102,
    "stateCode": "S15",
    "stateName": "Meghalaya",
    "districtCode": "S1501",
    "districtName": "WEST JAINTIA HILLS",
    "acNumber": 2,
    "acName": "JOWAI",
    "partNumber": 39,
    "partName": "MYNTHONG A",
    "lat": 25.4434703,
    "lon": 92.1973181
  },
  {
    "partId": 103,
    "stateCode": "S15",
    "stateName": "Meghalaya",
    "districtCode": "S1501",
    "districtName": "WEST JAINTIA HILLS",
    "acNumber": 2,
    "acName": "JOWAI",
    "partNumber": 40,
    "partName": "MYNTHONG B",
    "lat": 25.4434703,
    "lon": 92.1973181
  },
  {
    "partId": 104,
    "stateCode": "S15",
    "stateName": "Meghalaya",
    "districtCode": "S1501",
    "districtName": "WEST JAINTIA HILLS",
    "acNumber": 2,
    "acName": "JOWAI",
    "partNumber": 41,
    "partName": "CHUTWAKHU A (MALE)",
    "lat": 25.4434703,
    "lon": 92.1973181
  },
  {
    "partId": 105,
    "stateCode": "S15",
    "stateName": "Meghalaya",
    "districtCode": "S1501",
    "districtName": "WEST JAINTIA HILLS",
    "acNumber": 2,
    "acName": "JOWAI",
    "partNumber": 42,
    "partName": "CHUTWAKHU B (FEMALE)",
    "lat": 25.4434703,
    "lon": 92.1973181
  },
  {
    "partId": 106,
    "stateCode": "S15",
    "stateName": "Meghalaya",
    "districtCode": "S1501",
    "districtName": "WEST JAINTIA HILLS",
    "acNumber": 2,
    "acName": "JOWAI",
    "partNumber": 43,
    "partName": "KHIMUSNIANG A (MALE)",
    "lat": 25.4434703,
    "lon": 92.1973181
  },
  {
    "partId": 107,
    "stateCode": "S15",
    "stateName": "Meghalaya",
    "districtCode": "S1501",
    "districtName": "WEST JAINTIA HILLS",
    "acNumber": 2,
    "acName": "JOWAI",
    "partNumber": 44,
    "partName": "KHIMUSNIANG B (FEMALE)",
    "lat": 25.4434703,
    "lon": 92.1973181
  },
  {
    "partId": 108,
    "stateCode": "S15",
    "stateName": "Meghalaya",
    "districtCode": "S1501",
    "districtName": "WEST JAINTIA HILLS",
    "acNumber": 2,
    "acName": "JOWAI",
    "partNumber": 45,
    "partName": "MISSION COMPOUND A (MALE)",
    "lat": 25.4434703,
    "lon": 92.1973181
  },
  {
    "partId": 109,
    "stateCode": "S15",
    "stateName": "Meghalaya",
    "districtCode": "S1501",
    "districtName": "WEST JAINTIA HILLS",
    "acNumber": 2,
    "acName": "JOWAI",
    "partNumber": 46,
    "partName": "MISSION COMPOUND B (FEMALE)",
    "lat": 25.4434703,
    "lon": 92.1973181
  },
  {
    "partId": 110,
    "stateCode": "S15",
    "stateName": "Meghalaya",
    "districtCode": "S1501",
    "districtName": "WEST JAINTIA HILLS",
    "acNumber": 2,
    "acName": "JOWAI",
    "partNumber": 47,
    "partName": "CHILLIANGRAIJ A",
    "lat": 25.4434703,
    "lon": 92.1973181
  },
  {
    "partId": 111,
    "stateCode": "S15",
    "stateName": "Meghalaya",
    "districtCode": "S1501",
    "districtName": "WEST JAINTIA HILLS",
    "acNumber": 2,
    "acName": "JOWAI",
    "partNumber": 48,
    "partName": "CHILLIANGRAIJ B",
    "lat": 25.4425965,
    "lon": 92.29882747091773
  },
  {
    "partId": 112,
    "stateCode": "S15",
    "stateName": "Meghalaya",
    "districtCode": "S1501",
    "districtName": "WEST JAINTIA HILLS",
    "acNumber": 2,
    "acName": "JOWAI",
    "partNumber": 49,
    "partName": "DULONG A (MALE)",
    "lat": 25.4434703,
    "lon": 92.1973181
  },
  {
    "partId": 113,
    "stateCode": "S15",
    "stateName": "Meghalaya",
    "districtCode": "S1501",
    "districtName": "WEST JAINTIA HILLS",
    "acNumber": 2,
    "acName": "JOWAI",
    "partNumber": 50,
    "partName": "DULONG B (FEMALE)",
    "lat": 25.4434703,
    "lon": 92.1973181
  },
  {
    "partId": 114,
    "stateCode": "S15",
    "stateName": "Meghalaya",
    "districtCode": "S1501",
    "districtName": "WEST JAINTIA HILLS",
    "acNumber": 2,
    "acName": "JOWAI",
    "partNumber": 51,
    "partName": "DULONG C (MALE)",
    "lat": 25.4434703,
    "lon": 92.1973181
  },
  {
    "partId": 115,
    "stateCode": "S15",
    "stateName": "Meghalaya",
    "districtCode": "S1501",
    "districtName": "WEST JAINTIA HILLS",
    "acNumber": 2,
    "acName": "JOWAI",
    "partNumber": 52,
    "partName": "DULONG D (FEMALE)",
    "lat": 25.4434703,
    "lon": 92.1973181
  },
  {
    "partId": 116,
    "stateCode": "S15",
    "stateName": "Meghalaya",
    "districtCode": "S1501",
    "districtName": "WEST JAINTIA HILLS",
    "acNumber": 2,
    "acName": "JOWAI",
    "partNumber": 53,
    "partName": "TPEPPALE",
    "lat": 25.4434703,
    "lon": 92.1973181
  },
  {
    "partId": 117,
    "stateCode": "S15",
    "stateName": "Meghalaya",
    "districtCode": "S1501",
    "districtName": "WEST JAINTIA HILLS",
    "acNumber": 2,
    "acName": "JOWAI",
    "partNumber": 54,
    "partName": "PANALIAR A (MALE)",
    "lat": 25.4434703,
    "lon": 92.1973181
  },
  {
    "partId": 118,
    "stateCode": "S15",
    "stateName": "Meghalaya",
    "districtCode": "S1501",
    "districtName": "WEST JAINTIA HILLS",
    "acNumber": 2,
    "acName": "JOWAI",
    "partNumber": 55,
    "partName": "PANALIAR B (FEMALE)",
    "lat": 25.4434703,
    "lon": 92.1973181
  },
  {
    "partId": 119,
    "stateCode": "S15",
    "stateName": "Meghalaya",
    "districtCode": "S1501",
    "districtName": "WEST JAINTIA HILLS",
    "acNumber": 2,
    "acName": "JOWAI",
    "partNumber": 56,
    "partName": "IONGPIAH A (MALE)",
    "lat": 25.4434703,
    "lon": 92.1973181
  },
  {
    "partId": 120,
    "stateCode": "S15",
    "stateName": "Meghalaya",
    "districtCode": "S1501",
    "districtName": "WEST JAINTIA HILLS",
    "acNumber": 2,
    "acName": "JOWAI",
    "partNumber": 57,
    "partName": "IONGPIAH B (FEMALE)",
    "lat": 25.4434703,
    "lon": 92.1973181
  },
  {
    "partId": 176,
    "stateCode": "S15",
    "stateName": "Meghalaya",
    "districtCode": "S1501",
    "districtName": "WEST JAINTIA HILLS",
    "acNumber": 4,
    "acName": "MOWKAIAW",
    "partNumber": 1,
    "partName": "THADBAMON",
    "lat": 25.4425965,
    "lon": 92.29882747091773
  },
  {
    "partId": 177,
    "stateCode": "S15",
    "stateName": "Meghalaya",
    "districtCode": "S1501",
    "districtName": "WEST JAINTIA HILLS",
    "acNumber": 4,
    "acName": "MOWKAIAW",
    "partNumber": 2,
    "partName": "LATYMPHU A (MALE)",
    "lat": 25.4425965,
    "lon": 92.29882747091773
  },
  {
    "partId": 178,
    "stateCode": "S15",
    "stateName": "Meghalaya",
    "districtCode": "S1501",
    "districtName": "WEST JAINTIA HILLS",
    "acNumber": 4,
    "acName": "MOWKAIAW",
    "partNumber": 3,
    "partName": "LATYMPHU B (FEMALE)",
    "lat": 25.4425965,
    "lon": 92.29882747091773
  },
  {
    "partId": 179,
    "stateCode": "S15",
    "stateName": "Meghalaya",
    "districtCode": "S1501",
    "districtName": "WEST JAINTIA HILLS",
    "acNumber": 4,
    "acName": "MOWKAIAW",
    "partNumber": 4,
    "partName": "MUKROH A (MALE)",
    "lat": 25.4425965,
    "lon": 92.29882747091773
  },
  {
    "partId": 180,
    "stateCode": "S15",
    "stateName": "Meghalaya",
    "districtCode": "S1501",
    "districtName": "WEST JAINTIA HILLS",
    "acNumber": 4,
    "acName": "MOWKAIAW",
    "partNumber": 5,
    "partName": "MUKROH B (FEMALE)",
    "lat": 25.4425965,
    "lon": 92.29882747091773
  },
  {
    "partId": 181,
    "stateCode": "S15",
    "stateName": "Meghalaya",
    "districtCode": "S1501",
    "districtName": "WEST JAINTIA HILLS",
    "acNumber": 4,
    "acName": "MOWKAIAW",
    "partNumber": 6,
    "partName": "SABA",
    "lat": 25.4425965,
    "lon": 92.29882747091773
  },
  {
    "partId": 182,
    "stateCode": "S15",
    "stateName": "Meghalaya",
    "districtCode": "S1501",
    "districtName": "WEST JAINTIA HILLS",
    "acNumber": 4,
    "acName": "MOWKAIAW",
    "partNumber": 7,
    "partName": "BARATO A",
    "lat": 25.6052549,
    "lon": 92.4524711
  },
  {
    "partId": 183,
    "stateCode": "S15",
    "stateName": "Meghalaya",
    "districtCode": "S1501",
    "districtName": "WEST JAINTIA HILLS",
    "acNumber": 4,
    "acName": "MOWKAIAW",
    "partNumber": 8,
    "partName": "BARATO C",
    "lat": 25.6052549,
    "lon": 92.4524711
  },
  {
    "partId": 184,
    "stateCode": "S15",
    "stateName": "Meghalaya",
    "districtCode": "S1501",
    "districtName": "WEST JAINTIA HILLS",
    "acNumber": 4,
    "acName": "MOWKAIAW",
    "partNumber": 9,
    "partName": "BARATO B",
    "lat": 25.6052549,
    "lon": 92.4524711
  },
  {
    "partId": 185,
    "stateCode": "S15",
    "stateName": "Meghalaya",
    "districtCode": "S1501",
    "districtName": "WEST JAINTIA HILLS",
    "acNumber": 4,
    "acName": "MOWKAIAW",
    "partNumber": 10,
    "partName": "BARATO D",
    "lat": 25.6052549,
    "lon": 92.4524711
  },
  {
    "partId": 186,
    "stateCode": "S15",
    "stateName": "Meghalaya",
    "districtCode": "S1501",
    "districtName": "WEST JAINTIA HILLS",
    "acNumber": 4,
    "acName": "MOWKAIAW",
    "partNumber": 11,
    "partName": "MAITDEIN",
    "lat": 25.4425965,
    "lon": 92.29882747091773
  },
  {
    "partId": 187,
    "stateCode": "S15",
    "stateName": "Meghalaya",
    "districtCode": "S1501",
    "districtName": "WEST JAINTIA HILLS",
    "acNumber": 4,
    "acName": "MOWKAIAW",
    "partNumber": 12,
    "partName": "IONGKYNSHUR",
    "lat": 25.4425965,
    "lon": 92.29882747091773
  },
  {
    "partId": 188,
    "stateCode": "S15",
    "stateName": "Meghalaya",
    "districtCode": "S1501",
    "districtName": "WEST JAINTIA HILLS",
    "acNumber": 4,
    "acName": "MOWKAIAW",
    "partNumber": 13,
    "partName": "THANGRAIN A (MALE)",
    "lat": 25.4425965,
    "lon": 92.29882747091773
  },
  {
    "partId": 189,
    "stateCode": "S15",
    "stateName": "Meghalaya",
    "districtCode": "S1501",
    "districtName": "WEST JAINTIA HILLS",
    "acNumber": 4,
    "acName": "MOWKAIAW",
    "partNumber": 14,
    "partName": "THANGRAIN B (FEMALE)",
    "lat": 25.4425965,
    "lon": 92.29882747091773
  },
  {
    "partId": 190,
    "stateCode": "S15",
    "stateName": "Meghalaya",
    "districtCode": "S1501",
    "districtName": "WEST JAINTIA HILLS",
    "acNumber": 4,
    "acName": "MOWKAIAW",
    "partNumber": 15,
    "partName": "SHILLIANG MYNTANG",
    "lat": 25.5627257,
    "lon": 92.3686289
  },
  {
    "partId": 191,
    "stateCode": "S15",
    "stateName": "Meghalaya",
    "districtCode": "S1501",
    "districtName": "WEST JAINTIA HILLS",
    "acNumber": 4,
    "acName": "MOWKAIAW",
    "partNumber": 16,
    "partName": "THADSNING",
    "lat": 25.4425965,
    "lon": 92.29882747091773
  },
  {
    "partId": 192,
    "stateCode": "S15",
    "stateName": "Meghalaya",
    "districtCode": "S1501",
    "districtName": "WEST JAINTIA HILLS",
    "acNumber": 4,
    "acName": "MOWKAIAW",
    "partNumber": 17,
    "partName": "SAMATAN",
    "lat": 25.4425965,
    "lon": 92.29882747091773
  },
  {
    "partId": 193,
    "stateCode": "S15",
    "stateName": "Meghalaya",
    "districtCode": "S1501",
    "districtName": "WEST JAINTIA HILLS",
    "acNumber": 4,
    "acName": "MOWKAIAW",
    "partNumber": 18,
    "partName": "MULUM",
    "lat": 25.4425965,
    "lon": 92.29882747091773
  },
  {
    "partId": 194,
    "stateCode": "S15",
    "stateName": "Meghalaya",
    "districtCode": "S1501",
    "districtName": "WEST JAINTIA HILLS",
    "acNumber": 4,
    "acName": "MOWKAIAW",
    "partNumber": 19,
    "partName": "NONGKYNRIH",
    "lat": 25.4425965,
    "lon": 92.29882747091773
  },
  {
    "partId": 195,
    "stateCode": "S15",
    "stateName": "Meghalaya",
    "districtCode": "S1501",
    "districtName": "WEST JAINTIA HILLS",
    "acNumber": 4,
    "acName": "MOWKAIAW",
    "partNumber": 20,
    "partName": "LASKEIN A",
    "lat": 25.5195852,
    "lon": 92.4344622
  },
  {
    "partId": 196,
    "stateCode": "S15",
    "stateName": "Meghalaya",
    "districtCode": "S1501",
    "districtName": "WEST JAINTIA HILLS",
    "acNumber": 4,
    "acName": "MOWKAIAW",
    "partNumber": 21,
    "partName": "LASKEIN B",
    "lat": 25.5195852,
    "lon": 92.4344622
  },
  {
    "partId": 197,
    "stateCode": "S15",
    "stateName": "Meghalaya",
    "districtCode": "S1501",
    "districtName": "WEST JAINTIA HILLS",
    "acNumber": 4,
    "acName": "MOWKAIAW",
    "partNumber": 22,
    "partName": "MOWKAIAW A",
    "lat": 25.4425965,
    "lon": 92.29882747091773
  },
  {
    "partId": 198,
    "stateCode": "S15",
    "stateName": "Meghalaya",
    "districtCode": "S1501",
    "districtName": "WEST JAINTIA HILLS",
    "acNumber": 4,
    "acName": "MOWKAIAW",
    "partNumber": 23,
    "partName": "MOWKAIAW D",
    "lat": 25.4425965,
    "lon": 92.29882747091773
  },
  {
    "partId": 199,
    "stateCode": "S15",
    "stateName": "Meghalaya",
    "districtCode": "S1501",
    "districtName": "WEST JAINTIA HILLS",
    "acNumber": 4,
    "acName": "MOWKAIAW",
    "partNumber": 24,
    "partName": "MOWKAIAW B (MALE)",
    "lat": 25.4425965,
    "lon": 92.29882747091773
  },
  {
    "partId": 200,
    "stateCode": "S15",
    "stateName": "Meghalaya",
    "districtCode": "S1501",
    "districtName": "WEST JAINTIA HILLS",
    "acNumber": 4,
    "acName": "MOWKAIAW",
    "partNumber": 25,
    "partName": "MOWKAIAW C (FEMALE)",
    "lat": 25.4425965,
    "lon": 92.29882747091773
  },
  {
    "partId": 201,
    "stateCode": "S15",
    "stateName": "Meghalaya",
    "districtCode": "S1501",
    "districtName": "WEST JAINTIA HILLS",
    "acNumber": 4,
    "acName": "MOWKAIAW",
    "partNumber": 26,
    "partName": "KYRWEN",
    "lat": 25.4425965,
    "lon": 92.29882747091773
  },
  {
    "partId": 202,
    "stateCode": "S15",
    "stateName": "Meghalaya",
    "districtCode": "S1501",
    "districtName": "WEST JAINTIA HILLS",
    "acNumber": 4,
    "acName": "MOWKAIAW",
    "partNumber": 27,
    "partName": "SAHSNIANG B(MALE)",
    "lat": 25.4425965,
    "lon": 92.29882747091773
  },
  {
    "partId": 203,
    "stateCode": "S15",
    "stateName": "Meghalaya",
    "districtCode": "S1501",
    "districtName": "WEST JAINTIA HILLS",
    "acNumber": 4,
    "acName": "MOWKAIAW",
    "partNumber": 28,
    "partName": "SAHSNIANG B(FEMALE)",
    "lat": 25.4425965,
    "lon": 92.29882747091773
  },
  {
    "partId": 204,
    "stateCode": "S15",
    "stateName": "Meghalaya",
    "districtCode": "S1501",
    "districtName": "WEST JAINTIA HILLS",
    "acNumber": 4,
    "acName": "MOWKAIAW",
    "partNumber": 29,
    "partName": "SAHSNIANG A",
    "lat": 25.4425965,
    "lon": 92.29882747091773
  },
  {
    "partId": 205,
    "stateCode": "S15",
    "stateName": "Meghalaya",
    "districtCode": "S1501",
    "districtName": "WEST JAINTIA HILLS",
    "acNumber": 4,
    "acName": "MOWKAIAW",
    "partNumber": 30,
    "partName": "SAHSNIANG C",
    "lat": 25.4425965,
    "lon": 92.29882747091773
  },
  {
    "partId": 206,
    "stateCode": "S15",
    "stateName": "Meghalaya",
    "districtCode": "S1501",
    "districtName": "WEST JAINTIA HILLS",
    "acNumber": 4,
    "acName": "MOWKAIAW",
    "partNumber": 31,
    "partName": "MOOSHROT A",
    "lat": 25.4425965,
    "lon": 92.29882747091773
  },
  {
    "partId": 207,
    "stateCode": "S15",
    "stateName": "Meghalaya",
    "districtCode": "S1501",
    "districtName": "WEST JAINTIA HILLS",
    "acNumber": 4,
    "acName": "MOWKAIAW",
    "partNumber": 32,
    "partName": "MOOSHROT B",
    "lat": 25.4425965,
    "lon": 92.29882747091773
  },
  {
    "partId": 208,
    "stateCode": "S15",
    "stateName": "Meghalaya",
    "districtCode": "S1501",
    "districtName": "WEST JAINTIA HILLS",
    "acNumber": 4,
    "acName": "MOWKAIAW",
    "partNumber": 33,
    "partName": "TUM TUM A",
    "lat": 25.4425965,
    "lon": 92.29882747091773
  },
  {
    "partId": 209,
    "stateCode": "S15",
    "stateName": "Meghalaya",
    "districtCode": "S1501",
    "districtName": "WEST JAINTIA HILLS",
    "acNumber": 4,
    "acName": "MOWKAIAW",
    "partNumber": 34,
    "partName": "TUM TUM B",
    "lat": 25.4425965,
    "lon": 92.29882747091773
  },
  {
    "partId": 210,
    "stateCode": "S15",
    "stateName": "Meghalaya",
    "districtCode": "S1501",
    "districtName": "WEST JAINTIA HILLS",
    "acNumber": 4,
    "acName": "MOWKAIAW",
    "partNumber": 35,
    "partName": "MUKHAP A (MALE)",
    "lat": 25.4425965,
    "lon": 92.29882747091773
  },
  {
    "partId": 211,
    "stateCode": "S15",
    "stateName": "Meghalaya",
    "districtCode": "S1501",
    "districtName": "WEST JAINTIA HILLS",
    "acNumber": 4,
    "acName": "MOWKAIAW",
    "partNumber": 36,
    "partName": "MUKHAP B (FEMALE)",
    "lat": 25.4425965,
    "lon": 92.29882747091773
  },
  {
    "partId": 212,
    "stateCode": "S15",
    "stateName": "Meghalaya",
    "districtCode": "S1501",
    "districtName": "WEST JAINTIA HILLS",
    "acNumber": 4,
    "acName": "MOWKAIAW",
    "partNumber": 37,
    "partName": "MUKHAP C",
    "lat": 25.4425965,
    "lon": 92.29882747091773
  },
  {
    "partId": 213,
    "stateCode": "S15",
    "stateName": "Meghalaya",
    "districtCode": "S1501",
    "districtName": "WEST JAINTIA HILLS",
    "acNumber": 4,
    "acName": "MOWKAIAW",
    "partNumber": 38,
    "partName": "MOWTYRSHIAH B(M)",
    "lat": 25.4425965,
    "lon": 92.29882747091773
  },
  {
    "partId": 214,
    "stateCode": "S15",
    "stateName": "Meghalaya",
    "districtCode": "S1501",
    "districtName": "WEST JAINTIA HILLS",
    "acNumber": 4,
    "acName": "MOWKAIAW",
    "partNumber": 39,
    "partName": "MOWTYRSHIAH B(F)",
    "lat": 25.4425965,
    "lon": 92.29882747091773
  },
  {
    "partId": 215,
    "stateCode": "S15",
    "stateName": "Meghalaya",
    "districtCode": "S1501",
    "districtName": "WEST JAINTIA HILLS",
    "acNumber": 4,
    "acName": "MOWKAIAW",
    "partNumber": 40,
    "partName": "MOWTYRSHIAH A(M)",
    "lat": 25.4425965,
    "lon": 92.29882747091773
  },
  {
    "partId": 216,
    "stateCode": "S15",
    "stateName": "Meghalaya",
    "districtCode": "S1501",
    "districtName": "WEST JAINTIA HILLS",
    "acNumber": 4,
    "acName": "MOWKAIAW",
    "partNumber": 41,
    "partName": "MOWTYRSHIAH A(F)",
    "lat": 25.4425965,
    "lon": 92.29882747091773
  },
  {
    "partId": 217,
    "stateCode": "S15",
    "stateName": "Meghalaya",
    "districtCode": "S1501",
    "districtName": "WEST JAINTIA HILLS",
    "acNumber": 4,
    "acName": "MOWKAIAW",
    "partNumber": 42,
    "partName": "KHONSHNONG",
    "lat": 25.4425965,
    "lon": 92.29882747091773
  },
  {
    "partId": 218,
    "stateCode": "S15",
    "stateName": "Meghalaya",
    "districtCode": "S1501",
    "districtName": "WEST JAINTIA HILLS",
    "acNumber": 4,
    "acName": "MOWKAIAW",
    "partNumber": 43,
    "partName": "NONGRYNGKOH",
    "lat": 25.4425965,
    "lon": 92.29882747091773
  },
  {
    "partId": 219,
    "stateCode": "S15",
    "stateName": "Meghalaya",
    "districtCode": "S1501",
    "districtName": "WEST JAINTIA HILLS",
    "acNumber": 4,
    "acName": "MOWKAIAW",
    "partNumber": 44,
    "partName": "MYNKSAN",
    "lat": 25.4425965,
    "lon": 92.29882747091773
  },
  {
    "partId": 220,
    "stateCode": "S15",
    "stateName": "Meghalaya",
    "districtCode": "S1501",
    "districtName": "WEST JAINTIA HILLS",
    "acNumber": 4,
    "acName": "MOWKAIAW",
    "partNumber": 45,
    "partName": "UMSALAIT",
    "lat": 25.4425965,
    "lon": 92.29882747091773
  },
  {
    "partId": 221,
    "stateCode": "S15",
    "stateName": "Meghalaya",
    "districtCode": "S1501",
    "districtName": "WEST JAINTIA HILLS",
    "acNumber": 4,
    "acName": "MOWKAIAW",
    "partNumber": 46,
    "partName": "THANGTHRING",
    "lat": 25.4425965,
    "lon": 92.29882747091773
  },
  {
    "partId": 222,
    "stateCode": "S15",
    "stateName": "Meghalaya",
    "districtCode": "S1501",
    "districtName": "WEST JAINTIA HILLS",
    "acNumber": 4,
    "acName": "MOWKAIAW",
    "partNumber": 47,
    "partName": "IOOKSI A",
    "lat": 25.4425965,
    "lon": 92.29882747091773
  },
  {
    "partId": 223,
    "stateCode": "S15",
    "stateName": "Meghalaya",
    "districtCode": "S1501",
    "districtName": "WEST JAINTIA HILLS",
    "acNumber": 4,
    "acName": "MOWKAIAW",
    "partNumber": 48,
    "partName": "IOOKSI B",
    "lat": 25.4425965,
    "lon": 92.29882747091773
  },
  {
    "partId": 224,
    "stateCode": "S15",
    "stateName": "Meghalaya",
    "districtCode": "S1501",
    "districtName": "WEST JAINTIA HILLS",
    "acNumber": 4,
    "acName": "MOWKAIAW",
    "partNumber": 49,
    "partName": "IOOKSI KYANMYNSAR THLONGMOO",
    "lat": 25.4425965,
    "lon": 92.29882747091773
  },
  {
    "partId": 225,
    "stateCode": "S15",
    "stateName": "Meghalaya",
    "districtCode": "S1501",
    "districtName": "WEST JAINTIA HILLS",
    "acNumber": 4,
    "acName": "MOWKAIAW",
    "partNumber": 50,
    "partName": "LAKADONG",
    "lat": 25.4425965,
    "lon": 92.29882747091773
  },
  {
    "partId": 226,
    "stateCode": "S15",
    "stateName": "Meghalaya",
    "districtCode": "S1501",
    "districtName": "WEST JAINTIA HILLS",
    "acNumber": 4,
    "acName": "MOWKAIAW",
    "partNumber": 51,
    "partName": "SAPHAI POHRTIANG A (MALE)",
    "lat": 25.4425965,
    "lon": 92.29882747091773
  },
  {
    "partId": 227,
    "stateCode": "S15",
    "stateName": "Meghalaya",
    "districtCode": "S1501",
    "districtName": "WEST JAINTIA HILLS",
    "acNumber": 4,
    "acName": "MOWKAIAW",
    "partNumber": 52,
    "partName": "SAPHAI POHRTIANG B (FEMALE)",
    "lat": 25.4425965,
    "lon": 92.29882747091773
  },
  {
    "partId": 228,
    "stateCode": "S15",
    "stateName": "Meghalaya",
    "districtCode": "S1501",
    "districtName": "WEST JAINTIA HILLS",
    "acNumber": 4,
    "acName": "MOWKAIAW",
    "partNumber": 53,
    "partName": "RUDKUPLI IAWTHYMME",
    "lat": 25.4425965,
    "lon": 92.29882747091773
  },
  {
    "partId": 229,
    "stateCode": "S15",
    "stateName": "Meghalaya",
    "districtCode": "S1501",
    "districtName": "WEST JAINTIA HILLS",
    "acNumber": 4,
    "acName": "MOWKAIAW",
    "partNumber": 54,
    "partName": "UMDEINLIN",
    "lat": 25.4425965,
    "lon": 92.29882747091773
  },
  {
    "partId": 230,
    "stateCode": "S15",
    "stateName": "Meghalaya",
    "districtCode": "S1501",
    "districtName": "WEST JAINTIA HILLS",
    "acNumber": 4,
    "acName": "MOWKAIAW",
    "partNumber": 55,
    "partName": "PRIANG",
    "lat": 25.4425965,
    "lon": 92.29882747091773
  },
  {
    "partId": 3560,
    "stateCode": "S15",
    "stateName": "Meghalaya",
    "districtCode": "S1501",
    "districtName": "WEST JAINTIA HILLS",
    "acNumber": 1,
    "acName": "NARTIANG",
    "partNumber": 1,
    "partName": "UMLADANG",
    "lat": 25.5736564,
    "lon": 92.2170103
  },
  {
    "partId": 3561,
    "stateCode": "S15",
    "stateName": "Meghalaya",
    "districtCode": "S1501",
    "districtName": "WEST JAINTIA HILLS",
    "acNumber": 1,
    "acName": "NARTIANG",
    "partNumber": 2,
    "partName": "RAKABAH",
    "lat": 25.5736564,
    "lon": 92.2170103
  },
  {
    "partId": 3562,
    "stateCode": "S15",
    "stateName": "Meghalaya",
    "districtCode": "S1501",
    "districtName": "WEST JAINTIA HILLS",
    "acNumber": 1,
    "acName": "NARTIANG",
    "partNumber": 3,
    "partName": "NONGRIMBAMBTHONG",
    "lat": 25.5736564,
    "lon": 92.2170103
  },
  {
    "partId": 3563,
    "stateCode": "S15",
    "stateName": "Meghalaya",
    "districtCode": "S1501",
    "districtName": "WEST JAINTIA HILLS",
    "acNumber": 1,
    "acName": "NARTIANG",
    "partNumber": 4,
    "partName": "MOOKBU",
    "lat": 25.5736564,
    "lon": 92.2170103
  },
  {
    "partId": 3564,
    "stateCode": "S15",
    "stateName": "Meghalaya",
    "districtCode": "S1501",
    "districtName": "WEST JAINTIA HILLS",
    "acNumber": 1,
    "acName": "NARTIANG",
    "partNumber": 5,
    "partName": "MOOBAKHON",
    "lat": 25.5736564,
    "lon": 92.2170103
  },
  {
    "partId": 3565,
    "stateCode": "S15",
    "stateName": "Meghalaya",
    "districtCode": "S1501",
    "districtName": "WEST JAINTIA HILLS",
    "acNumber": 1,
    "acName": "NARTIANG",
    "partNumber": 6,
    "partName": "NONGTHYMME SEHLAMA",
    "lat": 25.5736564,
    "lon": 92.2170103
  },
  {
    "partId": 3566,
    "stateCode": "S15",
    "stateName": "Meghalaya",
    "districtCode": "S1501",
    "districtName": "WEST JAINTIA HILLS",
    "acNumber": 1,
    "acName": "NARTIANG",
    "partNumber": 7,
    "partName": "KSEHRYNSHANG",
    "lat": 25.5736564,
    "lon": 92.2170103
  },
  {
    "partId": 3567,
    "stateCode": "S15",
    "stateName": "Meghalaya",
    "districtCode": "S1501",
    "districtName": "WEST JAINTIA HILLS",
    "acNumber": 1,
    "acName": "NARTIANG",
    "partNumber": 8,
    "partName": "NAMDONG B (MALE)",
    "lat": 25.5736564,
    "lon": 92.2170103
  },
  {
    "partId": 3568,
    "stateCode": "S15",
    "stateName": "Meghalaya",
    "districtCode": "S1501",
    "districtName": "WEST JAINTIA HILLS",
    "acNumber": 1,
    "acName": "NARTIANG",
    "partNumber": 9,
    "partName": "NAMDONG C (FEMALE)",
    "lat": 25.4425965,
    "lon": 92.29882747091773
  },
  {
    "partId": 3623,
    "stateCode": "S15",
    "stateName": "Meghalaya",
    "districtCode": "S1501",
    "districtName": "WEST JAINTIA HILLS",
    "acNumber": 1,
    "acName": "NARTIANG",
    "partNumber": 10,
    "partName": "MUKHNANG",
    "lat": 25.5736564,
    "lon": 92.2170103
  },
  {
    "partId": 3569,
    "stateCode": "S15",
    "stateName": "Meghalaya",
    "districtCode": "S1501",
    "districtName": "WEST JAINTIA HILLS",
    "acNumber": 1,
    "acName": "NARTIANG",
    "partNumber": 11,
    "partName": "MUKOH",
    "lat": 25.5736564,
    "lon": 92.2170103
  },
  {
    "partId": 3570,
    "stateCode": "S15",
    "stateName": "Meghalaya",
    "districtCode": "S1501",
    "districtName": "WEST JAINTIA HILLS",
    "acNumber": 1,
    "acName": "NARTIANG",
    "partNumber": 12,
    "partName": "UMJALISIAW",
    "lat": 25.5736564,
    "lon": 92.2170103
  },
  {
    "partId": 3571,
    "stateCode": "S15",
    "stateName": "Meghalaya",
    "districtCode": "S1501",
    "districtName": "WEST JAINTIA HILLS",
    "acNumber": 1,
    "acName": "NARTIANG",
    "partNumber": 13,
    "partName": "NAMDONG A",
    "lat": 25.5736564,
    "lon": 92.2170103
  },
  {
    "partId": 3572,
    "stateCode": "S15",
    "stateName": "Meghalaya",
    "districtCode": "S1501",
    "districtName": "WEST JAINTIA HILLS",
    "acNumber": 1,
    "acName": "NARTIANG",
    "partNumber": 14,
    "partName": "THADMYNRI",
    "lat": 25.5736564,
    "lon": 92.2170103
  },
  {
    "partId": 3573,
    "stateCode": "S15",
    "stateName": "Meghalaya",
    "districtCode": "S1501",
    "districtName": "WEST JAINTIA HILLS",
    "acNumber": 1,
    "acName": "NARTIANG",
    "partNumber": 15,
    "partName": "SAITSAMA A (MALE)",
    "lat": 25.5736564,
    "lon": 92.2170103
  },
  {
    "partId": 3574,
    "stateCode": "S15",
    "stateName": "Meghalaya",
    "districtCode": "S1501",
    "districtName": "WEST JAINTIA HILLS",
    "acNumber": 1,
    "acName": "NARTIANG",
    "partNumber": 16,
    "partName": "SAITSAMA B (FEMALE)",
    "lat": 25.5736564,
    "lon": 92.2170103
  },
  {
    "partId": 3575,
    "stateCode": "S15",
    "stateName": "Meghalaya",
    "districtCode": "S1501",
    "districtName": "WEST JAINTIA HILLS",
    "acNumber": 1,
    "acName": "NARTIANG",
    "partNumber": 17,
    "partName": "TAMU A",
    "lat": 25.5736564,
    "lon": 92.2170103
  },
  {
    "partId": 3576,
    "stateCode": "S15",
    "stateName": "Meghalaya",
    "districtCode": "S1501",
    "districtName": "WEST JAINTIA HILLS",
    "acNumber": 1,
    "acName": "NARTIANG",
    "partNumber": 18,
    "partName": "TAMU B",
    "lat": 25.5736564,
    "lon": 92.2170103
  },
  {
    "partId": 3577,
    "stateCode": "S15",
    "stateName": "Meghalaya",
    "districtCode": "S1501",
    "districtName": "WEST JAINTIA HILLS",
    "acNumber": 1,
    "acName": "NARTIANG",
    "partNumber": 19,
    "partName": "LUMLAKHIAT",
    "lat": 25.5736564,
    "lon": 92.2170103
  },
  {
    "partId": 3578,
    "stateCode": "S15",
    "stateName": "Meghalaya",
    "districtCode": "S1501",
    "districtName": "WEST JAINTIA HILLS",
    "acNumber": 1,
    "acName": "NARTIANG",
    "partNumber": 20,
    "partName": "KHANDULI A (MALE)",
    "lat": 25.4425965,
    "lon": 92.29882747091773
  },
  {
    "partId": 3579,
    "stateCode": "S15",
    "stateName": "Meghalaya",
    "districtCode": "S1501",
    "districtName": "WEST JAINTIA HILLS",
    "acNumber": 1,
    "acName": "NARTIANG",
    "partNumber": 21,
    "partName": "KHANDULI B (FEMALE)",
    "lat": 25.5736564,
    "lon": 92.2170103
  },
  {
    "partId": 3580,
    "stateCode": "S15",
    "stateName": "Meghalaya",
    "districtCode": "S1501",
    "districtName": "WEST JAINTIA HILLS",
    "acNumber": 1,
    "acName": "NARTIANG",
    "partNumber": 22,
    "partName": "NONGLATEM",
    "lat": 25.6029737,
    "lon": 92.1872068
  },
  {
    "partId": 3581,
    "stateCode": "S15",
    "stateName": "Meghalaya",
    "districtCode": "S1501",
    "districtName": "WEST JAINTIA HILLS",
    "acNumber": 1,
    "acName": "NARTIANG",
    "partNumber": 23,
    "partName": "BAMKAMAR",
    "lat": 25.5736564,
    "lon": 92.2170103
  },
  {
    "partId": 3582,
    "stateCode": "S15",
    "stateName": "Meghalaya",
    "districtCode": "S1501",
    "districtName": "WEST JAINTIA HILLS",
    "acNumber": 1,
    "acName": "NARTIANG",
    "partNumber": 24,
    "partName": "MOORATHUD",
    "lat": 25.5736564,
    "lon": 92.2170103
  },
  {
    "partId": 3583,
    "stateCode": "S15",
    "stateName": "Meghalaya",
    "districtCode": "S1501",
    "districtName": "WEST JAINTIA HILLS",
    "acNumber": 1,
    "acName": "NARTIANG",
    "partNumber": 25,
    "partName": "MYNSNGAT A (MALE)",
    "lat": 25.5736564,
    "lon": 92.2170103
  },
  {
    "partId": 3584,
    "stateCode": "S15",
    "stateName": "Meghalaya",
    "districtCode": "S1501",
    "districtName": "WEST JAINTIA HILLS",
    "acNumber": 1,
    "acName": "NARTIANG",
    "partNumber": 26,
    "partName": "MYNSNGAT B (FEMALE)",
    "lat": 25.5736564,
    "lon": 92.2170103
  },
  {
    "partId": 3585,
    "stateCode": "S15",
    "stateName": "Meghalaya",
    "districtCode": "S1501",
    "districtName": "WEST JAINTIA HILLS",
    "acNumber": 1,
    "acName": "NARTIANG",
    "partNumber": 27,
    "partName": "MYNSNGAT RAKHWI",
    "lat": 25.5736564,
    "lon": 92.2170103
  },
  {
    "partId": 3586,
    "stateCode": "S15",
    "stateName": "Meghalaya",
    "districtCode": "S1501",
    "districtName": "WEST JAINTIA HILLS",
    "acNumber": 1,
    "acName": "NARTIANG",
    "partNumber": 28,
    "partName": "MOORAP",
    "lat": 25.5736564,
    "lon": 92.2170103
  },
  {
    "partId": 3587,
    "stateCode": "S15",
    "stateName": "Meghalaya",
    "districtCode": "S1501",
    "districtName": "WEST JAINTIA HILLS",
    "acNumber": 1,
    "acName": "NARTIANG",
    "partNumber": 29,
    "partName": "NONGKHROH A",
    "lat": 25.5736564,
    "lon": 92.2170103
  },
  {
    "partId": 3588,
    "stateCode": "S15",
    "stateName": "Meghalaya",
    "districtCode": "S1501",
    "districtName": "WEST JAINTIA HILLS",
    "acNumber": 1,
    "acName": "NARTIANG",
    "partNumber": 30,
    "partName": "NONGKHROH B",
    "lat": 25.5736564,
    "lon": 92.2170103
  },
  {
    "partId": 3589,
    "stateCode": "S15",
    "stateName": "Meghalaya",
    "districtCode": "S1501",
    "districtName": "WEST JAINTIA HILLS",
    "acNumber": 1,
    "acName": "NARTIANG",
    "partNumber": 31,
    "partName": "THADMUSEM",
    "lat": 25.5736564,
    "lon": 92.2170103
  },
  {
    "partId": 3590,
    "stateCode": "S15",
    "stateName": "Meghalaya",
    "districtCode": "S1501",
    "districtName": "WEST JAINTIA HILLS",
    "acNumber": 1,
    "acName": "NARTIANG",
    "partNumber": 32,
    "partName": "MOODYMMAI A (MALE)",
    "lat": 25.5736564,
    "lon": 92.2170103
  },
  {
    "partId": 3591,
    "stateCode": "S15",
    "stateName": "Meghalaya",
    "districtCode": "S1501",
    "districtName": "WEST JAINTIA HILLS",
    "acNumber": 1,
    "acName": "NARTIANG",
    "partNumber": 33,
    "partName": "MOODYMMAI B (FEMALE)",
    "lat": 25.5736564,
    "lon": 92.2170103
  },
  {
    "partId": 3592,
    "stateCode": "S15",
    "stateName": "Meghalaya",
    "districtCode": "S1501",
    "districtName": "WEST JAINTIA HILLS",
    "acNumber": 1,
    "acName": "NARTIANG",
    "partNumber": 34,
    "partName": "MOODYMMAI C",
    "lat": 25.5736564,
    "lon": 92.2170103
  },
  {
    "partId": 3593,
    "stateCode": "S15",
    "stateName": "Meghalaya",
    "districtCode": "S1501",
    "districtName": "WEST JAINTIA HILLS",
    "acNumber": 1,
    "acName": "NARTIANG",
    "partNumber": 35,
    "partName": "TYRSHANG",
    "lat": 25.5293172,
    "lon": 92.1505102
  },
  {
    "partId": 3594,
    "stateCode": "S15",
    "stateName": "Meghalaya",
    "districtCode": "S1501",
    "districtName": "WEST JAINTIA HILLS",
    "acNumber": 1,
    "acName": "NARTIANG",
    "partNumber": 36,
    "partName": "SOHPHOH",
    "lat": 25.5650795,
    "lon": 92.161411
  },
  {
    "partId": 3595,
    "stateCode": "S15",
    "stateName": "Meghalaya",
    "districtCode": "S1501",
    "districtName": "WEST JAINTIA HILLS",
    "acNumber": 1,
    "acName": "NARTIANG",
    "partNumber": 37,
    "partName": "LARNAI",
    "lat": 25.5736564,
    "lon": 92.2170103
  },
  {
    "partId": 3596,
    "stateCode": "S15",
    "stateName": "Meghalaya",
    "districtCode": "S1501",
    "districtName": "WEST JAINTIA HILLS",
    "acNumber": 1,
    "acName": "NARTIANG",
    "partNumber": 38,
    "partName": "NARTIANG A",
    "lat": 25.5736564,
    "lon": 92.2170103
  },
  {
    "partId": 3597,
    "stateCode": "S15",
    "stateName": "Meghalaya",
    "districtCode": "S1501",
    "districtName": "WEST JAINTIA HILLS",
    "acNumber": 1,
    "acName": "NARTIANG",
    "partNumber": 39,
    "partName": "NARTIANG B",
    "lat": 25.5736564,
    "lon": 92.2170103
  },
  {
    "partId": 3598,
    "stateCode": "S15",
    "stateName": "Meghalaya",
    "districtCode": "S1501",
    "districtName": "WEST JAINTIA HILLS",
    "acNumber": 1,
    "acName": "NARTIANG",
    "partNumber": 40,
    "partName": "MOODOP A",
    "lat": 25.5736564,
    "lon": 92.2170103
  },
  {
    "partId": 3599,
    "stateCode": "S15",
    "stateName": "Meghalaya",
    "districtCode": "S1501",
    "districtName": "WEST JAINTIA HILLS",
    "acNumber": 1,
    "acName": "NARTIANG",
    "partNumber": 41,
    "partName": "MOODOP B",
    "lat": 25.5736564,
    "lon": 92.2170103
  },
  {
    "partId": 3600,
    "stateCode": "S15",
    "stateName": "Meghalaya",
    "districtCode": "S1501",
    "districtName": "WEST JAINTIA HILLS",
    "acNumber": 1,
    "acName": "NARTIANG",
    "partNumber": 42,
    "partName": "UMMULONG A",
    "lat": 25.5736564,
    "lon": 92.2170103
  },
  {
    "partId": 3601,
    "stateCode": "S15",
    "stateName": "Meghalaya",
    "districtCode": "S1501",
    "districtName": "WEST JAINTIA HILLS",
    "acNumber": 1,
    "acName": "NARTIANG",
    "partNumber": 43,
    "partName": "UMMULONG LUMKYNSAW",
    "lat": 25.5736564,
    "lon": 92.2170103
  },
  {
    "partId": 3602,
    "stateCode": "S15",
    "stateName": "Meghalaya",
    "districtCode": "S1501",
    "districtName": "WEST JAINTIA HILLS",
    "acNumber": 1,
    "acName": "NARTIANG",
    "partNumber": 44,
    "partName": "UMMULONG B (MALE)",
    "lat": 25.5736564,
    "lon": 92.2170103
  },
  {
    "partId": 3603,
    "stateCode": "S15",
    "stateName": "Meghalaya",
    "districtCode": "S1501",
    "districtName": "WEST JAINTIA HILLS",
    "acNumber": 1,
    "acName": "NARTIANG",
    "partNumber": 45,
    "partName": "UMMULONG C (FEMALE)",
    "lat": 25.5736564,
    "lon": 92.2170103
  },
  {
    "partId": 3604,
    "stateCode": "S15",
    "stateName": "Meghalaya",
    "districtCode": "S1501",
    "districtName": "WEST JAINTIA HILLS",
    "acNumber": 1,
    "acName": "NARTIANG",
    "partNumber": 46,
    "partName": "MOOKYNDUR",
    "lat": 25.5736564,
    "lon": 92.2170103
  },
  {
    "partId": 3605,
    "stateCode": "S15",
    "stateName": "Meghalaya",
    "districtCode": "S1501",
    "districtName": "WEST JAINTIA HILLS",
    "acNumber": 1,
    "acName": "NARTIANG",
    "partNumber": 47,
    "partName": "MASKUT",
    "lat": 25.5736564,
    "lon": 92.2170103
  },
  {
    "partId": 3606,
    "stateCode": "S15",
    "stateName": "Meghalaya",
    "districtCode": "S1501",
    "districtName": "WEST JAINTIA HILLS",
    "acNumber": 1,
    "acName": "NARTIANG",
    "partNumber": 48,
    "partName": "WAHIAJER A (MALE)",
    "lat": 25.5736564,
    "lon": 92.2170103
  },
  {
    "partId": 3607,
    "stateCode": "S15",
    "stateName": "Meghalaya",
    "districtCode": "S1501",
    "districtName": "WEST JAINTIA HILLS",
    "acNumber": 1,
    "acName": "NARTIANG",
    "partNumber": 49,
    "partName": "WAHIAJER RC",
    "lat": 25.5736564,
    "lon": 92.2170103
  },
  {
    "partId": 3608,
    "stateCode": "S15",
    "stateName": "Meghalaya",
    "districtCode": "S1501",
    "districtName": "WEST JAINTIA HILLS",
    "acNumber": 1,
    "acName": "NARTIANG",
    "partNumber": 50,
    "partName": "WAHIAJER B (FEMALE)",
    "lat": 25.5736564,
    "lon": 92.2170103
  },
  {
    "partId": 3609,
    "stateCode": "S15",
    "stateName": "Meghalaya",
    "districtCode": "S1501",
    "districtName": "WEST JAINTIA HILLS",
    "acNumber": 1,
    "acName": "NARTIANG",
    "partNumber": 51,
    "partName": "WAHIAJER RC",
    "lat": 25.5736564,
    "lon": 92.2170103
  },
  {
    "partId": 3610,
    "stateCode": "S15",
    "stateName": "Meghalaya",
    "districtCode": "S1501",
    "districtName": "WEST JAINTIA HILLS",
    "acNumber": 1,
    "acName": "NARTIANG",
    "partNumber": 52,
    "partName": "WAHIAJER C (MALE)",
    "lat": 25.5736564,
    "lon": 92.2170103
  },
  {
    "partId": 3611,
    "stateCode": "S15",
    "stateName": "Meghalaya",
    "districtCode": "S1501",
    "districtName": "WEST JAINTIA HILLS",
    "acNumber": 1,
    "acName": "NARTIANG",
    "partNumber": 53,
    "partName": "WAHIAJER LUMBHAHDAKHA",
    "lat": 25.5736564,
    "lon": 92.2170103
  },
  {
    "partId": 3612,
    "stateCode": "S15",
    "stateName": "Meghalaya",
    "districtCode": "S1501",
    "districtName": "WEST JAINTIA HILLS",
    "acNumber": 1,
    "acName": "NARTIANG",
    "partNumber": 54,
    "partName": "WAHIAJER D (FEMALE)",
    "lat": 25.5736564,
    "lon": 92.2170103
  },
  {
    "partId": 3613,
    "stateCode": "S15",
    "stateName": "Meghalaya",
    "districtCode": "S1501",
    "districtName": "WEST JAINTIA HILLS",
    "acNumber": 1,
    "acName": "NARTIANG",
    "partNumber": 55,
    "partName": "WAHIAJER LUMBHAHDAKHA",
    "lat": 25.5736564,
    "lon": 92.2170103
  },
  {
    "partId": 3614,
    "stateCode": "S15",
    "stateName": "Meghalaya",
    "districtCode": "S1501",
    "districtName": "WEST JAINTIA HILLS",
    "acNumber": 1,
    "acName": "NARTIANG",
    "partNumber": 56,
    "partName": "MUPLIANG A",
    "lat": 25.5456553,
    "lon": 92.2051674
  },
  {
    "partId": 3615,
    "stateCode": "S15",
    "stateName": "Meghalaya",
    "districtCode": "S1501",
    "districtName": "WEST JAINTIA HILLS",
    "acNumber": 1,
    "acName": "NARTIANG",
    "partNumber": 57,
    "partName": "MUPLIANG B",
    "lat": 25.5456553,
    "lon": 92.2051674
  },
  {
    "partId": 3616,
    "stateCode": "S15",
    "stateName": "Meghalaya",
    "districtCode": "S1501",
    "districtName": "WEST JAINTIA HILLS",
    "acNumber": 1,
    "acName": "NARTIANG",
    "partNumber": 58,
    "partName": "MYRJAI",
    "lat": 25.5736564,
    "lon": 92.2170103
  },
  {
    "partId": 3617,
    "stateCode": "S15",
    "stateName": "Meghalaya",
    "districtCode": "S1501",
    "districtName": "WEST JAINTIA HILLS",
    "acNumber": 1,
    "acName": "NARTIANG",
    "partNumber": 59,
    "partName": "MYNKREM",
    "lat": 25.5736564,
    "lon": 92.2170103
  },
  {
    "partId": 3618,
    "stateCode": "S15",
    "stateName": "Meghalaya",
    "districtCode": "S1501",
    "districtName": "WEST JAINTIA HILLS",
    "acNumber": 1,
    "acName": "NARTIANG",
    "partNumber": 60,
    "partName": "IONGSNIEJ TAKHNIANG",
    "lat": 25.5736564,
    "lon": 92.2170103
  },
  {
    "partId": 3619,
    "stateCode": "S15",
    "stateName": "Meghalaya",
    "districtCode": "S1501",
    "districtName": "WEST JAINTIA HILLS",
    "acNumber": 1,
    "acName": "NARTIANG",
    "partNumber": 61,
    "partName": "SANARO",
    "lat": 25.5736564,
    "lon": 92.2170103
  },
  {
    "partId": 3620,
    "stateCode": "S15",
    "stateName": "Meghalaya",
    "districtCode": "S1501",
    "districtName": "WEST JAINTIA HILLS",
    "acNumber": 1,
    "acName": "NARTIANG",
    "partNumber": 62,
    "partName": "PDEINIADAW",
    "lat": 25.5736564,
    "lon": 92.2170103
  },
  {
    "partId": 3621,
    "stateCode": "S15",
    "stateName": "Meghalaya",
    "districtCode": "S1501",
    "districtName": "WEST JAINTIA HILLS",
    "acNumber": 1,
    "acName": "NARTIANG",
    "partNumber": 63,
    "partName": "LAPANGAP A",
    "lat": 25.5736564,
    "lon": 92.2170103
  },
  {
    "partId": 3622,
    "stateCode": "S15",
    "stateName": "Meghalaya",
    "districtCode": "S1501",
    "districtName": "WEST JAINTIA HILLS",
    "acNumber": 1,
    "acName": "NARTIANG",
    "partNumber": 64,
    "partName": "LAPANGAP B",
    "lat": 25.5736564,
    "lon": 92.2170103
  },
  {
    "partId": 121,
    "stateCode": "S15",
    "stateName": "Meghalaya",
    "districtCode": "S1501",
    "districtName": "WEST JAINTIA HILLS",
    "acNumber": 3,
    "acName": "RALIANG",
    "partNumber": 1,
    "partName": "IONGLWIT A (MALE)",
    "lat": 25.4989014,
    "lon": 92.3935443
  },
  {
    "partId": 122,
    "stateCode": "S15",
    "stateName": "Meghalaya",
    "districtCode": "S1501",
    "districtName": "WEST JAINTIA HILLS",
    "acNumber": 3,
    "acName": "RALIANG",
    "partNumber": 2,
    "partName": "IONGLWIT B (FEMALE)",
    "lat": 25.4989014,
    "lon": 92.3935443
  },
  {
    "partId": 123,
    "stateCode": "S15",
    "stateName": "Meghalaya",
    "districtCode": "S1501",
    "districtName": "WEST JAINTIA HILLS",
    "acNumber": 3,
    "acName": "RALIANG",
    "partNumber": 3,
    "partName": "LUMSTONG",
    "lat": 25.4989014,
    "lon": 92.3935443
  },
  {
    "partId": 124,
    "stateCode": "S15",
    "stateName": "Meghalaya",
    "districtCode": "S1501",
    "districtName": "WEST JAINTIA HILLS",
    "acNumber": 3,
    "acName": "RALIANG",
    "partNumber": 4,
    "partName": "NONGJNGI A(MALE)",
    "lat": 25.4989014,
    "lon": 92.3935443
  },
  {
    "partId": 125,
    "stateCode": "S15",
    "stateName": "Meghalaya",
    "districtCode": "S1501",
    "districtName": "WEST JAINTIA HILLS",
    "acNumber": 3,
    "acName": "RALIANG",
    "partNumber": 5,
    "partName": "NONGJNGI B(FEMALE)",
    "lat": 25.4989014,
    "lon": 92.3935443
  },
  {
    "partId": 126,
    "stateCode": "S15",
    "stateName": "Meghalaya",
    "districtCode": "S1501",
    "districtName": "WEST JAINTIA HILLS",
    "acNumber": 3,
    "acName": "RALIANG",
    "partNumber": 6,
    "partName": "NANGBAH PRESBYTERIAN A (MALE)",
    "lat": 25.4989014,
    "lon": 92.3935443
  },
  {
    "partId": 127,
    "stateCode": "S15",
    "stateName": "Meghalaya",
    "districtCode": "S1501",
    "districtName": "WEST JAINTIA HILLS",
    "acNumber": 3,
    "acName": "RALIANG",
    "partNumber": 7,
    "partName": "NANGBAH PRESBYTERIAN B (FEMALE)",
    "lat": 25.4989014,
    "lon": 92.3935443
  },
  {
    "partId": 128,
    "stateCode": "S15",
    "stateName": "Meghalaya",
    "districtCode": "S1501",
    "districtName": "WEST JAINTIA HILLS",
    "acNumber": 3,
    "acName": "RALIANG",
    "partNumber": 8,
    "partName": "NANGBAH IAWMUSIANG A",
    "lat": 25.4989014,
    "lon": 92.3935443
  },
  {
    "partId": 129,
    "stateCode": "S15",
    "stateName": "Meghalaya",
    "districtCode": "S1501",
    "districtName": "WEST JAINTIA HILLS",
    "acNumber": 3,
    "acName": "RALIANG",
    "partNumber": 9,
    "partName": "NANGBAH IAWMUSIANG B",
    "lat": 25.4989014,
    "lon": 92.3935443
  },
  {
    "partId": 130,
    "stateCode": "S15",
    "stateName": "Meghalaya",
    "districtCode": "S1501",
    "districtName": "WEST JAINTIA HILLS",
    "acNumber": 3,
    "acName": "RALIANG",
    "partNumber": 10,
    "partName": "NANGBAH MULANG A(MALE)",
    "lat": 25.4989014,
    "lon": 92.3935443
  },
  {
    "partId": 131,
    "stateCode": "S15",
    "stateName": "Meghalaya",
    "districtCode": "S1501",
    "districtName": "WEST JAINTIA HILLS",
    "acNumber": 3,
    "acName": "RALIANG",
    "partNumber": 11,
    "partName": "NANGBAH MULANG B(FEMALE)",
    "lat": 25.4989014,
    "lon": 92.3935443
  },
  {
    "partId": 132,
    "stateCode": "S15",
    "stateName": "Meghalaya",
    "districtCode": "S1501",
    "districtName": "WEST JAINTIA HILLS",
    "acNumber": 3,
    "acName": "RALIANG",
    "partNumber": 12,
    "partName": "NANGBAH LUMCHOR",
    "lat": 25.4989014,
    "lon": 92.3935443
  },
  {
    "partId": 133,
    "stateCode": "S15",
    "stateName": "Meghalaya",
    "districtCode": "S1501",
    "districtName": "WEST JAINTIA HILLS",
    "acNumber": 3,
    "acName": "RALIANG",
    "partNumber": 13,
    "partName": "NANGBAH KYNDONGSYIEM A(MALE)",
    "lat": 25.4989014,
    "lon": 92.3935443
  },
  {
    "partId": 134,
    "stateCode": "S15",
    "stateName": "Meghalaya",
    "districtCode": "S1501",
    "districtName": "WEST JAINTIA HILLS",
    "acNumber": 3,
    "acName": "RALIANG",
    "partNumber": 14,
    "partName": "NANGBAH KYNDONGSYIEM B(FEMALE)",
    "lat": 25.4989014,
    "lon": 92.3935443
  },
  {
    "partId": 135,
    "stateCode": "S15",
    "stateName": "Meghalaya",
    "districtCode": "S1501",
    "districtName": "WEST JAINTIA HILLS",
    "acNumber": 3,
    "acName": "RALIANG",
    "partNumber": 15,
    "partName": "KYNDONGTUBER N",
    "lat": 25.4989014,
    "lon": 92.3935443
  },
  {
    "partId": 136,
    "stateCode": "S15",
    "stateName": "Meghalaya",
    "districtCode": "S1501",
    "districtName": "WEST JAINTIA HILLS",
    "acNumber": 3,
    "acName": "RALIANG",
    "partNumber": 16,
    "partName": "KYNDONGTUBER LUMKHANGDONG",
    "lat": 25.4989014,
    "lon": 92.3935443
  },
  {
    "partId": 137,
    "stateCode": "S15",
    "stateName": "Meghalaya",
    "districtCode": "S1501",
    "districtName": "WEST JAINTIA HILLS",
    "acNumber": 3,
    "acName": "RALIANG",
    "partNumber": 17,
    "partName": "KYNDONGTUBER LUM PRESBYTERIAN A",
    "lat": 25.4989014,
    "lon": 92.3935443
  },
  {
    "partId": 138,
    "stateCode": "S15",
    "stateName": "Meghalaya",
    "districtCode": "S1501",
    "districtName": "WEST JAINTIA HILLS",
    "acNumber": 3,
    "acName": "RALIANG",
    "partNumber": 18,
    "partName": "KYNDONGTUBER LUM PRESBYTERIAN B",
    "lat": 25.4989014,
    "lon": 92.3935443
  },
  {
    "partId": 139,
    "stateCode": "S15",
    "stateName": "Meghalaya",
    "districtCode": "S1501",
    "districtName": "WEST JAINTIA HILLS",
    "acNumber": 3,
    "acName": "RALIANG",
    "partNumber": 19,
    "partName": "PAMMANIK A(MALE)",
    "lat": 25.4989014,
    "lon": 92.3935443
  },
  {
    "partId": 140,
    "stateCode": "S15",
    "stateName": "Meghalaya",
    "districtCode": "S1501",
    "districtName": "WEST JAINTIA HILLS",
    "acNumber": 3,
    "acName": "RALIANG",
    "partNumber": 20,
    "partName": "PAMMANIK B(FEMALE)",
    "lat": 25.4989014,
    "lon": 92.3935443
  },
  {
    "partId": 141,
    "stateCode": "S15",
    "stateName": "Meghalaya",
    "districtCode": "S1501",
    "districtName": "WEST JAINTIA HILLS",
    "acNumber": 3,
    "acName": "RALIANG",
    "partNumber": 21,
    "partName": "MYNSO A (MALE)",
    "lat": 25.4989014,
    "lon": 92.3935443
  },
  {
    "partId": 142,
    "stateCode": "S15",
    "stateName": "Meghalaya",
    "districtCode": "S1501",
    "districtName": "WEST JAINTIA HILLS",
    "acNumber": 3,
    "acName": "RALIANG",
    "partNumber": 22,
    "partName": "MYNSO A (FEMALE)",
    "lat": 25.4989014,
    "lon": 92.3935443
  },
  {
    "partId": 143,
    "stateCode": "S15",
    "stateName": "Meghalaya",
    "districtCode": "S1501",
    "districtName": "WEST JAINTIA HILLS",
    "acNumber": 3,
    "acName": "RALIANG",
    "partNumber": 23,
    "partName": "MYNSO B (MALE)",
    "lat": 25.4989014,
    "lon": 92.3935443
  },
  {
    "partId": 144,
    "stateCode": "S15",
    "stateName": "Meghalaya",
    "districtCode": "S1501",
    "districtName": "WEST JAINTIA HILLS",
    "acNumber": 3,
    "acName": "RALIANG",
    "partNumber": 24,
    "partName": "MYNSO B (FEMALE)",
    "lat": 25.4425965,
    "lon": 92.29882747091773
  },
  {
    "partId": 145,
    "stateCode": "S15",
    "stateName": "Meghalaya",
    "districtCode": "S1501",
    "districtName": "WEST JAINTIA HILLS",
    "acNumber": 3,
    "acName": "RALIANG",
    "partNumber": 25,
    "partName": "PASYIH A (MALE)",
    "lat": 25.4989014,
    "lon": 92.3935443
  },
  {
    "partId": 146,
    "stateCode": "S15",
    "stateName": "Meghalaya",
    "districtCode": "S1501",
    "districtName": "WEST JAINTIA HILLS",
    "acNumber": 3,
    "acName": "RALIANG",
    "partNumber": 26,
    "partName": "PASYIH B (FEMALE)",
    "lat": 25.4989014,
    "lon": 92.3935443
  },
  {
    "partId": 147,
    "stateCode": "S15",
    "stateName": "Meghalaya",
    "districtCode": "S1501",
    "districtName": "WEST JAINTIA HILLS",
    "acNumber": 3,
    "acName": "RALIANG",
    "partNumber": 27,
    "partName": "THADMUTHLONG A",
    "lat": 25.4989014,
    "lon": 92.3935443
  },
  {
    "partId": 148,
    "stateCode": "S15",
    "stateName": "Meghalaya",
    "districtCode": "S1501",
    "districtName": "WEST JAINTIA HILLS",
    "acNumber": 3,
    "acName": "RALIANG",
    "partNumber": 28,
    "partName": "THADMUTHLONG C",
    "lat": 25.4989014,
    "lon": 92.3935443
  },
  {
    "partId": 149,
    "stateCode": "S15",
    "stateName": "Meghalaya",
    "districtCode": "S1501",
    "districtName": "WEST JAINTIA HILLS",
    "acNumber": 3,
    "acName": "RALIANG",
    "partNumber": 29,
    "partName": "THADMUTHLONG B (MALE)",
    "lat": 25.4989014,
    "lon": 92.3935443
  },
  {
    "partId": 150,
    "stateCode": "S15",
    "stateName": "Meghalaya",
    "districtCode": "S1501",
    "districtName": "WEST JAINTIA HILLS",
    "acNumber": 3,
    "acName": "RALIANG",
    "partNumber": 30,
    "partName": "THADMUTHLONG B (FEMALE)",
    "lat": 25.4989014,
    "lon": 92.3935443
  },
  {
    "partId": 151,
    "stateCode": "S15",
    "stateName": "Meghalaya",
    "districtCode": "S1501",
    "districtName": "WEST JAINTIA HILLS",
    "acNumber": 3,
    "acName": "RALIANG",
    "partNumber": 31,
    "partName": "THADMUTHLONG PHRAMER",
    "lat": 25.4989014,
    "lon": 92.3935443
  },
  {
    "partId": 152,
    "stateCode": "S15",
    "stateName": "Meghalaya",
    "districtCode": "S1501",
    "districtName": "WEST JAINTIA HILLS",
    "acNumber": 3,
    "acName": "RALIANG",
    "partNumber": 32,
    "partName": "MYNTKUNG",
    "lat": 25.4989014,
    "lon": 92.3935443
  },
  {
    "partId": 153,
    "stateCode": "S15",
    "stateName": "Meghalaya",
    "districtCode": "S1501",
    "districtName": "WEST JAINTIA HILLS",
    "acNumber": 3,
    "acName": "RALIANG",
    "partNumber": 33,
    "partName": "MUTHLONGRIM",
    "lat": 25.4989014,
    "lon": 92.3935443
  },
  {
    "partId": 154,
    "stateCode": "S15",
    "stateName": "Meghalaya",
    "districtCode": "S1501",
    "districtName": "WEST JAINTIA HILLS",
    "acNumber": 3,
    "acName": "RALIANG",
    "partNumber": 34,
    "partName": "SHANGPUNG POHSHNONG A",
    "lat": 25.4989014,
    "lon": 92.3935443
  },
  {
    "partId": 155,
    "stateCode": "S15",
    "stateName": "Meghalaya",
    "districtCode": "S1501",
    "districtName": "WEST JAINTIA HILLS",
    "acNumber": 3,
    "acName": "RALIANG",
    "partNumber": 35,
    "partName": "SHANGPUNG POHSHNONG B",
    "lat": 25.4989014,
    "lon": 92.3935443
  },
  {
    "partId": 156,
    "stateCode": "S15",
    "stateName": "Meghalaya",
    "districtCode": "S1501",
    "districtName": "WEST JAINTIA HILLS",
    "acNumber": 3,
    "acName": "RALIANG",
    "partNumber": 36,
    "partName": "SHANGPUNG POHSHNONG C",
    "lat": 25.4989014,
    "lon": 92.3935443
  },
  {
    "partId": 157,
    "stateCode": "S15",
    "stateName": "Meghalaya",
    "districtCode": "S1501",
    "districtName": "WEST JAINTIA HILLS",
    "acNumber": 3,
    "acName": "RALIANG",
    "partNumber": 37,
    "partName": "SHANGPUNG MISSION A (MALE)",
    "lat": 25.4989014,
    "lon": 92.3935443
  },
  {
    "partId": 158,
    "stateCode": "S15",
    "stateName": "Meghalaya",
    "districtCode": "S1501",
    "districtName": "WEST JAINTIA HILLS",
    "acNumber": 3,
    "acName": "RALIANG",
    "partNumber": 38,
    "partName": "SHANGPUNG MISSION B (FEMALE)",
    "lat": 25.4989014,
    "lon": 92.3935443
  },
  {
    "partId": 159,
    "stateCode": "S15",
    "stateName": "Meghalaya",
    "districtCode": "S1501",
    "districtName": "WEST JAINTIA HILLS",
    "acNumber": 3,
    "acName": "RALIANG",
    "partNumber": 39,
    "partName": "SHANGPUNG MOOSYIEM",
    "lat": 25.4989014,
    "lon": 92.3935443
  },
  {
    "partId": 160,
    "stateCode": "S15",
    "stateName": "Meghalaya",
    "districtCode": "S1501",
    "districtName": "WEST JAINTIA HILLS",
    "acNumber": 3,
    "acName": "RALIANG",
    "partNumber": 40,
    "partName": "KHLIEHRANGNAH A (MALE)",
    "lat": 25.4989014,
    "lon": 92.3935443
  },
  {
    "partId": 161,
    "stateCode": "S15",
    "stateName": "Meghalaya",
    "districtCode": "S1501",
    "districtName": "WEST JAINTIA HILLS",
    "acNumber": 3,
    "acName": "RALIANG",
    "partNumber": 41,
    "partName": "KHLIEHRANGNAH B (FEMALE)",
    "lat": 25.4425965,
    "lon": 92.29882747091773
  },
  {
    "partId": 162,
    "stateCode": "S15",
    "stateName": "Meghalaya",
    "districtCode": "S1501",
    "districtName": "WEST JAINTIA HILLS",
    "acNumber": 3,
    "acName": "RALIANG",
    "partNumber": 42,
    "partName": "KHLIEHMUSHUT SHANGPUNG",
    "lat": 25.4989014,
    "lon": 92.3935443
  },
  {
    "partId": 163,
    "stateCode": "S15",
    "stateName": "Meghalaya",
    "districtCode": "S1501",
    "districtName": "WEST JAINTIA HILLS",
    "acNumber": 3,
    "acName": "RALIANG",
    "partNumber": 43,
    "partName": "SHANGPUNG MOOLIBANG",
    "lat": 25.4989014,
    "lon": 92.3935443
  },
  {
    "partId": 164,
    "stateCode": "S15",
    "stateName": "Meghalaya",
    "districtCode": "S1501",
    "districtName": "WEST JAINTIA HILLS",
    "acNumber": 3,
    "acName": "RALIANG",
    "partNumber": 44,
    "partName": "MADANKYNSAW A (MALE)",
    "lat": 25.4989014,
    "lon": 92.3935443
  },
  {
    "partId": 165,
    "stateCode": "S15",
    "stateName": "Meghalaya",
    "districtCode": "S1501",
    "districtName": "WEST JAINTIA HILLS",
    "acNumber": 3,
    "acName": "RALIANG",
    "partNumber": 45,
    "partName": "MADANKYNSAW B (FEMALE)",
    "lat": 25.4989014,
    "lon": 92.3935443
  },
  {
    "partId": 166,
    "stateCode": "S15",
    "stateName": "Meghalaya",
    "districtCode": "S1501",
    "districtName": "WEST JAINTIA HILLS",
    "acNumber": 3,
    "acName": "RALIANG",
    "partNumber": 46,
    "partName": "MULIEH",
    "lat": 25.4989014,
    "lon": 92.3935443
  },
  {
    "partId": 167,
    "stateCode": "S15",
    "stateName": "Meghalaya",
    "districtCode": "S1501",
    "districtName": "WEST JAINTIA HILLS",
    "acNumber": 3,
    "acName": "RALIANG",
    "partNumber": 47,
    "partName": "RALIANG A",
    "lat": 25.4989014,
    "lon": 92.3935443
  },
  {
    "partId": 168,
    "stateCode": "S15",
    "stateName": "Meghalaya",
    "districtCode": "S1501",
    "districtName": "WEST JAINTIA HILLS",
    "acNumber": 3,
    "acName": "RALIANG",
    "partNumber": 48,
    "partName": "RALIANG DONG LUMSEHKOT",
    "lat": 25.4989014,
    "lon": 92.3935443
  },
  {
    "partId": 169,
    "stateCode": "S15",
    "stateName": "Meghalaya",
    "districtCode": "S1501",
    "districtName": "WEST JAINTIA HILLS",
    "acNumber": 3,
    "acName": "RALIANG",
    "partNumber": 49,
    "partName": "RALIANG B",
    "lat": 25.4989014,
    "lon": 92.3935443
  },
  {
    "partId": 170,
    "stateCode": "S15",
    "stateName": "Meghalaya",
    "districtCode": "S1501",
    "districtName": "WEST JAINTIA HILLS",
    "acNumber": 3,
    "acName": "RALIANG",
    "partNumber": 50,
    "partName": "MYNKREM",
    "lat": 25.4989014,
    "lon": 92.3935443
  },
  {
    "partId": 171,
    "stateCode": "S15",
    "stateName": "Meghalaya",
    "districtCode": "S1501",
    "districtName": "WEST JAINTIA HILLS",
    "acNumber": 3,
    "acName": "RALIANG",
    "partNumber": 51,
    "partName": "RTIANG S",
    "lat": 25.4989014,
    "lon": 92.3935443
  },
  {
    "partId": 172,
    "stateCode": "S15",
    "stateName": "Meghalaya",
    "districtCode": "S1501",
    "districtName": "WEST JAINTIA HILLS",
    "acNumber": 3,
    "acName": "RALIANG",
    "partNumber": 52,
    "partName": "BIAR",
    "lat": 25.4989014,
    "lon": 92.3935443
  },
  {
    "partId": 173,
    "stateCode": "S15",
    "stateName": "Meghalaya",
    "districtCode": "S1501",
    "districtName": "WEST JAINTIA HILLS",
    "acNumber": 3,
    "acName": "RALIANG",
    "partNumber": 53,
    "partName": "MYNSKA A(MALE)",
    "lat": 25.4989014,
    "lon": 92.3935443
  },
  {
    "partId": 174,
    "stateCode": "S15",
    "stateName": "Meghalaya",
    "districtCode": "S1501",
    "districtName": "WEST JAINTIA HILLS",
    "acNumber": 3,
    "acName": "RALIANG",
    "partNumber": 54,
    "partName": "MYNSKA B(FEMALE)",
    "lat": 25.4989014,
    "lon": 92.3935443
  },
  {
    "partId": 175,
    "stateCode": "S15",
    "stateName": "Meghalaya",
    "districtCode": "S1501",
    "districtName": "WEST JAINTIA HILLS",
    "acNumber": 3,
    "acName": "RALIANG",
    "partNumber": 55,
    "partName": "KHLOOKYNRIN",
    "lat": 25.4989014,
    "lon": 92.3935443
  }
]